{"total_count": 17, "jobs": [{"id": 5256047688, "run_id": 1867533284, "run_url": "https://api.github.com/repos/spack/spack/actions/runs/1867533284", "run_attempt": 1, "node_id": "CR_kwDOAPAIsc8AAAABOUjsSA", "head_sha": "e886a61a6c91a6cdaaf7587b15192087b62570d8", "url": "https://api.github.com/repos/spack/spack/actions/jobs/5256047688", "html_url": "https://github.com/spack/spack/actions/runs/1867533284/jobs/2628971144", "status": "completed", "conclusion": "success", "started_at": "2022-02-19T02:38:33Z", "completed_at": "2022-02-19T02:41:17Z", "name": "style", "steps": [{"name": "Set up job", "status": "completed", "conclusion": "success", "number": 1, "started_at": "2022-02-19T03:38:33.000+01:00", "completed_at": "2022-02-19T03:38:34.000+01:00"}, {"name": "Run actions/checkout@ec3a7ce113134d7a93b817d10a8272cb61118579", "status": "completed", "conclusion": "success", "number": 2, "started_at": "2022-02-19T03:38:34.000+01:00", "completed_at": "2022-02-19T03:38:55.000+01:00"}, {"name": "Run actions/setup-python@f38219332975fe8f9c04cca981d674bf22aea1d3", "status": "completed", "conclusion": "success", "number": 3, "started_at": "2022-02-19T03:38:55.000+01:00", "completed_at": "2022-02-19T03:38:55.000+01:00"}, {"name": "Install Python packages", "status": "completed", "conclusion": "success", "number": 4, "started_at": "2022-02-19T03:38:55.000+01:00", "completed_at": "2022-02-19T03:39:01.000+01:00"}, {"name": "Setup git configuration", "status": "completed", "conclusion": "success", "number": 5, "started_at": "2022-02-19T03:39:01.000+01:00", "completed_at": "2022-02-19T03:39:01.000+01:00"}, {"name": "Run style tests", "status": "completed", "conclusion": "success", "number": 6, "started_at": "2022-02-19T03:39:01.000+01:00", "completed_at": "2022-02-19T03:41:17.000+01:00"}, {"name": "Post Run actions/setup-python@f38219332975fe8f9c04cca981d674bf22aea1d3", "status": "completed", "conclusion": "success", "number": 11, "started_at": "2022-02-19T03:41:17.000+01:00", "completed_at": "2022-02-19T03:41:17.000+01:00"}, {"name": "Post Run actions/checkout@ec3a7ce113134d7a93b817d10a8272cb61118579", "status": "completed", "conclusion": "success", "number": 12, "started_at": "2022-02-19T03:41:17.000+01:00", "completed_at": "2022-02-19T03:41:17.000+01:00"}, {"name": "Complete job", "status": "completed", "conclusion": "success", "number": 13, "started_at": "2022-02-19T03:41:17.000+01:00", "completed_at": "2022-02-19T03:41:17.000+01:00"}], "check_run_url": "https://api.github.com/repos/spack/spack/check-runs/5256047688", "labels": ["ubuntu-latest"], "runner_id": 3, "runner_name": "GitHub Actions 3", "runner_group_id": 2, "runner_group_name": "GitHub Actions"}, {"id": 5256047716, "run_id": 1867533284, "run_url": "https://api.github.com/repos/spack/spack/actions/runs/1867533284", "run_attempt": 1, "node_id": "CR_kwDOAPAIsc8AAAABOUjsZA", "head_sha": "e886a61a6c91a6cdaaf7587b15192087b62570d8", "url": "https://api.github.com/repos/spack/spack/actions/jobs/5256047716", "html_url": "https://github.com/spack/spack/actions/runs/1867533284/jobs/2628971167", "status": "completed", "conclusion": "success", "started_at": "2022-02-19T02:38:34Z", "completed_at": "2022-02-19T02:39:02Z", "name": "validate", "steps": [{"name": "Set up job", "status": "completed", "conclusion": "success", "number": 1, "started_at": "2022-02-19T03:38:34.000+01:00", "completed_at": "2022-02-19T03:38:35.000+01:00"}, {"name": "Run actions/checkout@ec3a7ce113134d7a93b817d10a8272cb61118579", "status": "completed", "conclusion": "success", "number": 2, "started_at": "2022-02-19T03:38:35.000+01:00", "completed_at": "2022-02-19T03:38:39.000+01:00"}, {"name": "Run actions/setup-python@f38219332975fe8f9c04cca981d674bf22aea1d3", "status": "completed", "conclusion": "success", "number": 3, "started_at": "2022-02-19T03:38:39.000+01:00", "completed_at": "2022-02-19T03:38:39.000+01:00"}, {"name": "Install Python Packages", "status": "completed", "conclusion": "success", "number": 4, "started_at": "2022-02-19T03:38:39.000+01:00", "completed_at": "2022-02-19T03:38:41.000+01:00"}, {"name": "vermin (Spack's Core)", "status": "completed", "conclusion": "success", "number": 5, "started_at": "2022-02-19T03:38:41.000+01:00", "completed_at": "2022-02-19T03:38:47.000+01:00"}, {"name": "vermin (Repositories)", "status": "completed", "conclusion": "success", "number": 6, "started_at": "2022-02-19T03:38:47.000+01:00", "completed_at": "2022-02-19T03:39:02.000+01:00"}, {"name": "Post Run actions/setup-python@f38219332975fe8f9c04cca981d674bf22aea1d3", "status": "completed", "conclusion": "success", "number": 11, "started_at": "2022-02-19T03:39:02.000+01:00", "completed_at": "2022-02-19T03:39:02.000+01:00"}, {"name": "Post Run actions/checkout@ec3a7ce113134d7a93b817d10a8272cb61118579", "status": "completed", "conclusion": "success", "number": 12, "started_at": "2022-02-19T03:39:02.000+01:00", "completed_at": "2022-02-19T03:39:02.000+01:00"}, {"name": "Complete job", "status": "completed", "conclusion": "success", "number": 13, "started_at": "2022-02-19T03:39:02.000+01:00", "completed_at": "2022-02-19T03:39:02.000+01:00"}], "check_run_url": "https://api.github.com/repos/spack/spack/check-runs/5256047716", "labels": ["ubuntu-latest"], "runner_id": 1, "runner_name": "Hosted Agent", "runner_group_id": 2, "runner_group_name": "GitHub Actions"}, {"id": 5256047753, "run_id": 1867533284, "run_url": "https://api.github.com/repos/spack/spack/actions/runs/1867533284", "run_attempt": 1, "node_id": "CR_kwDOAPAIsc8AAAABOUjsiQ", "head_sha": "e886a61a6c91a6cdaaf7587b15192087b62570d8", "url": "https://api.github.com/repos/spack/spack/actions/jobs/5256047753", "html_url": "https://github.com/spack/spack/actions/runs/1867533284/jobs/2628971196", "status": "completed", "conclusion": "success", "started_at": "2022-02-19T02:38:31Z", "completed_at": "2022-02-19T02:38:53Z", "name": "changes", "steps": [{"name": "Set up job", "status": "completed", "conclusion": "success", "number": 1, "started_at": "2022-02-19T03:38:31.000+01:00", "completed_at": "2022-02-19T03:38:32.000+01:00"}, {"name": "Run actions/checkout@ec3a7ce113134d7a93b817d10a8272cb61118579", "status": "completed", "conclusion": "success", "number": 2, "started_at": "2022-02-19T03:38:32.000+01:00", "completed_at": "2022-02-19T03:38:53.000+01:00"}, {"name": "Run dorny/paths-filter@b2feaf19c27470162a626bd6fa8438ae5b263721", "status": "completed", "conclusion": "success", "number": 3, "started_at": "2022-02-19T03:38:53.000+01:00", "completed_at": "2022-02-19T03:38:53.000+01:00"}, {"name": "Run echo Core changes: false", "status": "completed", "conclusion": "success", "number": 4, "started_at": "2022-02-19T03:38:53.000+01:00", "completed_at": "2022-02-19T03:38:53.000+01:00"}, {"name": "Post Run actions/checkout@ec3a7ce113134d7a93b817d10a8272cb61118579", "status": "completed", "conclusion": "success", "number": 8, "started_at": "2022-02-19T03:38:53.000+01:00", "completed_at": "2022-02-19T03:38:53.000+01:00"}, {"name": "Complete job", "status": "completed", "conclusion": "success", "number": 9, "started_at": "2022-02-19T03:38:53.000+01:00", "completed_at": "2022-02-19T03:38:53.000+01:00"}], "check_run_url": "https://api.github.com/repos/spack/spack/check-runs/5256047753", "labels": ["ubuntu-latest"], "runner_id": 2, "runner_name": "GitHub Actions 2", "runner_group_id": 2, "runner_group_name": "GitHub Actions"}, {"id": 5256063216, "run_id": 1867533284, "run_url": "https://api.github.com/repos/spack/spack/actions/runs/1867533284", "run_attempt": 1, "node_id": "CR_kwDOAPAIsc8AAAABOUko8A", "head_sha": "e886a61a6c91a6cdaaf7587b15192087b62570d8", "url": "https://api.github.com/repos/spack/spack/actions/jobs/5256063216", "html_url": "https://github.com/spack/spack/actions/runs/1867533284/jobs/2628983512", "status": "completed", "conclusion": "success", "started_at": "2022-02-19T02:46:59Z", "completed_at": "2022-02-19T02:50:51Z", "name": "build (3.8)", "steps": [{"name": "Set up job", "status": "completed", "conclusion": "success", "number": 1, "started_at": "2022-02-19T03:46:59.000+01:00", "completed_at": "2022-02-19T03:47:02.000+01:00"}, {"name": "Run actions/checkout@ec3a7ce113134d7a93b817d10a8272cb61118579", "status": "completed", "conclusion": "success", "number": 2, "started_at": "2022-02-19T03:47:02.000+01:00", "completed_at": "2022-02-19T03:47:28.000+01:00"}, {"name": "Run actions/setup-python@f38219332975fe8f9c04cca981d674bf22aea1d3", "status": "completed", "conclusion": "success", "number": 3, "started_at": "2022-02-19T03:47:28.000+01:00", "completed_at": "2022-02-19T03:47:28.000+01:00"}, {"name": "Install Python packages", "status": "completed", "conclusion": "success", "number": 4, "started_at": "2022-02-19T03:47:28.000+01:00", "completed_at": "2022-02-19T03:47:38.000+01:00"}, {"name": "Setup Homebrew packages", "status": "completed", "conclusion": "success", "number": 5, "started_at": "2022-02-19T03:47:38.000+01:00", "completed_at": "2022-02-19T03:48:36.000+01:00"}, {"name": "Run unit tests", "status": "completed", "conclusion": "success", "number": 6, "started_at": "2022-02-19T03:48:36.000+01:00", "completed_at": "2022-02-19T03:50:50.000+01:00"}, {"name": "Run codecov/codecov-action@f32b3a3741e1053eb607407145bc9619351dc93b", "status": "completed", "conclusion": "skipped", "number": 7, "started_at": "2022-02-19T03:50:50.000+01:00", "completed_at": "2022-02-19T03:50:50.000+01:00"}, {"name": "Post Run actions/setup-python@f38219332975fe8f9c04cca981d674bf22aea1d3", "status": "completed", "conclusion": "success", "number": 13, "started_at": "2022-02-19T03:50:50.000+01:00", "completed_at": "2022-02-19T03:50:50.000+01:00"}, {"name": "Post Run actions/checkout@ec3a7ce113134d7a93b817d10a8272cb61118579", "status": "completed", "conclusion": "success", "number": 14, "started_at": "2022-02-19T03:50:50.000+01:00", "completed_at": "2022-02-19T03:50:51.000+01:00"}, {"name": "Complete job", "status": "completed", "conclusion": "success", "number": 15, "started_at": "2022-02-19T03:50:51.000+01:00", "completed_at": "2022-02-19T03:50:51.000+01:00"}], "check_run_url": "https://api.github.com/repos/spack/spack/check-runs/5256063216", "labels": ["macos-latest"], "runner_id": 4, "runner_name": "GitHub Actions 4", "runner_group_id": 2, "runner_group_name": "GitHub Actions"}, {"id": 5256063269, "run_id": 1867533284, "run_url": "https://api.github.com/repos/spack/spack/actions/runs/1867533284", "run_attempt": 1, "node_id": "CR_kwDOAPAIsc8AAAABOUkpJQ", "head_sha": "e886a61a6c91a6cdaaf7587b15192087b62570d8", "url": "https://api.github.com/repos/spack/spack/actions/jobs/5256063269", "html_url": "https://github.com/spack/spack/actions/runs/1867533284/jobs/2628983551", "status": "completed", "conclusion": "success", "started_at": "2022-02-19T02:41:29Z", "completed_at": "2022-02-19T02:44:48Z", "name": "clingo-cffi", "steps": [{"name": "Set up job", "status": "completed", "conclusion": "success", "number": 1, "started_at": "2022-02-19T03:41:29.000+01:00", "completed_at": "2022-02-19T03:41:30.000+01:00"}, {"name": "Run actions/checkout@ec3a7ce113134d7a93b817d10a8272cb61118579", "status": "completed", "conclusion": "success", "number": 2, "started_at": "2022-02-19T03:41:30.000+01:00", "completed_at": "2022-02-19T03:41:51.000+01:00"}, {"name": "Run actions/setup-python@f38219332975fe8f9c04cca981d674bf22aea1d3", "status": "completed", "conclusion": "success", "number": 3, "started_at": "2022-02-19T03:41:51.000+01:00", "completed_at": "2022-02-19T03:41:51.000+01:00"}, {"name": "Install System packages", "status": "completed", "conclusion": "success", "number": 4, "started_at": "2022-02-19T03:41:51.000+01:00", "completed_at": "2022-02-19T03:42:09.000+01:00"}, {"name": "Install Python packages", "status": "completed", "conclusion": "success", "number": 5, "started_at": "2022-02-19T03:42:09.000+01:00", "completed_at": "2022-02-19T03:42:15.000+01:00"}, {"name": "Setup git configuration", "status": "completed", "conclusion": "success", "number": 6, "started_at": "2022-02-19T03:42:15.000+01:00", "completed_at": "2022-02-19T03:42:15.000+01:00"}, {"name": "Run unit tests (full suite with coverage)", "status": "completed", "conclusion": "skipped", "number": 7, "started_at": "2022-02-19T03:42:15.000+01:00", "completed_at": "2022-02-19T03:42:15.000+01:00"}, {"name": "Run unit tests (reduced suite without coverage)", "status": "completed", "conclusion": "success", "number": 8, "started_at": "2022-02-19T03:42:15.000+01:00", "completed_at": "2022-02-19T03:44:48.000+01:00"}, {"name": "Run codecov/codecov-action@f32b3a3741e1053eb607407145bc9619351dc93b", "status": "completed", "conclusion": "skipped", "number": 9, "started_at": "2022-02-19T03:44:48.000+01:00", "completed_at": "2022-02-19T03:44:48.000+01:00"}, {"name": "Post Run actions/setup-python@f38219332975fe8f9c04cca981d674bf22aea1d3", "status": "completed", "conclusion": "success", "number": 17, "started_at": "2022-02-19T03:44:48.000+01:00", "completed_at": "2022-02-19T03:44:48.000+01:00"}, {"name": "Post Run actions/checkout@ec3a7ce113134d7a93b817d10a8272cb61118579", "status": "completed", "conclusion": "success", "number": 18, "started_at": "2022-02-19T03:44:48.000+01:00", "completed_at": "2022-02-19T03:44:48.000+01:00"}, {"name": "Complete job", "status": "completed", "conclusion": "success", "number": 19, "started_at": "2022-02-19T03:44:48.000+01:00", "completed_at": "2022-02-19T03:44:48.000+01:00"}], "check_run_url": "https://api.github.com/repos/spack/spack/check-runs/5256063269", "labels": ["ubuntu-latest"], "runner_id": 3, "runner_name": "GitHub Actions 3", "runner_group_id": 2, "runner_group_name": "GitHub Actions"}, {"id": 5256063295, "run_id": 1867533284, "run_url": "https://api.github.com/repos/spack/spack/actions/runs/1867533284", "run_attempt": 1, "node_id": "CR_kwDOAPAIsc8AAAABOUkpPw", "head_sha": "e886a61a6c91a6cdaaf7587b15192087b62570d8", "url": "https://api.github.com/repos/spack/spack/actions/jobs/5256063295", "html_url": "https://github.com/spack/spack/actions/runs/1867533284/jobs/2628983572", "status": "completed", "conclusion": "success", "started_at": "2022-02-19T02:41:30Z", "completed_at": "2022-02-19T02:42:41Z", "name": "package-audits", "steps": [{"name": "Set up job", "status": "completed", "conclusion": "success", "number": 1, "started_at": "2022-02-19T03:41:30.000+01:00", "completed_at": "2022-02-19T03:41:33.000+01:00"}, {"name": "Run actions/checkout@ec3a7ce113134d7a93b817d10a8272cb61118579", "status": "completed", "conclusion": "success", "number": 2, "started_at": "2022-02-19T03:41:33.000+01:00", "completed_at": "2022-02-19T03:41:36.000+01:00"}, {"name": "Run actions/setup-python@f38219332975fe8f9c04cca981d674bf22aea1d3", "status": "completed", "conclusion": "success", "number": 3, "started_at": "2022-02-19T03:41:36.000+01:00", "completed_at": "2022-02-19T03:41:36.000+01:00"}, {"name": "Install Python packages", "status": "completed", "conclusion": "success", "number": 4, "started_at": "2022-02-19T03:41:36.000+01:00", "completed_at": "2022-02-19T03:41:42.000+01:00"}, {"name": "Package audits (with coverage)", "status": "completed", "conclusion": "skipped", "number": 5, "started_at": "2022-02-19T03:41:42.000+01:00", "completed_at": "2022-02-19T03:41:42.000+01:00"}, {"name": "Package audits (wwithout coverage)", "status": "completed", "conclusion": "success", "number": 6, "started_at": "2022-02-19T03:41:42.000+01:00", "completed_at": "2022-02-19T03:42:40.000+01:00"}, {"name": "Run codecov/codecov-action@f32b3a3741e1053eb607407145bc9619351dc93b", "status": "completed", "conclusion": "skipped", "number": 7, "started_at": "2022-02-19T03:42:40.000+01:00", "completed_at": "2022-02-19T03:42:40.000+01:00"}, {"name": "Post Run actions/setup-python@f38219332975fe8f9c04cca981d674bf22aea1d3", "status": "completed", "conclusion": "success", "number": 13, "started_at": "2022-02-19T03:42:40.000+01:00", "completed_at": "2022-02-19T03:42:40.000+01:00"}, {"name": "Post Run actions/checkout@ec3a7ce113134d7a93b817d10a8272cb61118579", "status": "completed", "conclusion": "success", "number": 14, "started_at": "2022-02-19T03:42:40.000+01:00", "completed_at": "2022-02-19T03:42:40.000+01:00"}, {"name": "Complete job", "status": "completed", "conclusion": "success", "number": 15, "started_at": "2022-02-19T03:42:40.000+01:00", "completed_at": "2022-02-19T03:42:40.000+01:00"}], "check_run_url": "https://api.github.com/repos/spack/spack/check-runs/5256063295", "labels": ["ubuntu-latest"], "runner_id": 19, "runner_name": "GitHub Actions 19", "runner_group_id": 2, "runner_group_name": "GitHub Actions"}, {"id": 5256063316, "run_id": 1867533284, "run_url": "https://api.github.com/repos/spack/spack/actions/runs/1867533284", "run_attempt": 1, "node_id": "CR_kwDOAPAIsc8AAAABOUkpVA", "head_sha": "e886a61a6c91a6cdaaf7587b15192087b62570d8", "url": "https://api.github.com/repos/spack/spack/actions/jobs/5256063316", "html_url": "https://github.com/spack/spack/actions/runs/1867533284/jobs/2628983591", "status": "completed", "conclusion": "skipped", "started_at": "2022-02-19T02:41:22Z", "completed_at": "2022-02-19T02:41:22Z", "name": "rhel8-platform-python", "steps": [], "check_run_url": "https://api.github.com/repos/spack/spack/check-runs/5256063316", "labels": [], "runner_id": null, "runner_name": null, "runner_group_id": null, "runner_group_name": null}, {"id": 5256063354, "run_id": 1867533284, "run_url": "https://api.github.com/repos/spack/spack/actions/runs/1867533284", "run_attempt": 1, "node_id": "CR_kwDOAPAIsc8AAAABOUkpeg", "head_sha": "e886a61a6c91a6cdaaf7587b15192087b62570d8", "url": "https://api.github.com/repos/spack/spack/actions/jobs/5256063354", "html_url": "https://github.com/spack/spack/actions/runs/1867533284/jobs/2628983619", "status": "completed", "conclusion": "success", "started_at": "2022-02-19T02:41:30Z", "completed_at": "2022-02-19T02:49:13Z", "name": "shell", "steps": [{"name": "Set up job", "status": "completed", "conclusion": "success", "number": 1, "started_at": "2022-02-19T03:41:30.000+01:00", "completed_at": "2022-02-19T03:41:31.000+01:00"}, {"name": "Run actions/checkout@ec3a7ce113134d7a93b817d10a8272cb61118579", "status": "completed", "conclusion": "success", "number": 2, "started_at": "2022-02-19T03:41:31.000+01:00", "completed_at": "2022-02-19T03:41:52.000+01:00"}, {"name": "Run actions/setup-python@f38219332975fe8f9c04cca981d674bf22aea1d3", "status": "completed", "conclusion": "success", "number": 3, "started_at": "2022-02-19T03:41:52.000+01:00", "completed_at": "2022-02-19T03:41:52.000+01:00"}, {"name": "Install System packages", "status": "completed", "conclusion": "success", "number": 4, "started_at": "2022-02-19T03:41:52.000+01:00", "completed_at": "2022-02-19T03:42:10.000+01:00"}, {"name": "Install Python packages", "status": "completed", "conclusion": "success", "number": 5, "started_at": "2022-02-19T03:42:10.000+01:00", "completed_at": "2022-02-19T03:42:16.000+01:00"}, {"name": "Setup git configuration", "status": "completed", "conclusion": "success", "number": 6, "started_at": "2022-02-19T03:42:16.000+01:00", "completed_at": "2022-02-19T03:42:16.000+01:00"}, {"name": "Run shell tests (without coverage)", "status": "completed", "conclusion": "success", "number": 7, "started_at": "2022-02-19T03:42:16.000+01:00", "completed_at": "2022-02-19T03:49:13.000+01:00"}, {"name": "Run shell tests (with coverage)", "status": "completed", "conclusion": "skipped", "number": 8, "started_at": "2022-02-19T03:49:13.000+01:00", "completed_at": "2022-02-19T03:49:13.000+01:00"}, {"name": "Run codecov/codecov-action@f32b3a3741e1053eb607407145bc9619351dc93b", "status": "completed", "conclusion": "skipped", "number": 9, "started_at": "2022-02-19T03:49:13.000+01:00", "completed_at": "2022-02-19T03:49:13.000+01:00"}, {"name": "Post Run actions/setup-python@f38219332975fe8f9c04cca981d674bf22aea1d3", "status": "completed", "conclusion": "success", "number": 17, "started_at": "2022-02-19T03:49:13.000+01:00", "completed_at": "2022-02-19T03:49:13.000+01:00"}, {"name": "Post Run actions/checkout@ec3a7ce113134d7a93b817d10a8272cb61118579", "status": "completed", "conclusion": "success", "number": 18, "started_at": "2022-02-19T03:49:13.000+01:00", "completed_at": "2022-02-19T03:49:13.000+01:00"}, {"name": "Complete job", "status": "completed", "conclusion": "success", "number": 19, "started_at": "2022-02-19T03:49:13.000+01:00", "completed_at": "2022-02-19T03:49:13.000+01:00"}], "check_run_url": "https://api.github.com/repos/spack/spack/check-runs/5256063354", "labels": ["ubuntu-latest"], "runner_id": 20, "runner_name": "GitHub Actions 20", "runner_group_id": 2, "runner_group_name": "GitHub Actions"}, {"id": 5256063374, "run_id": 1867533284, "run_url": "https://api.github.com/repos/spack/spack/actions/runs/1867533284", "run_attempt": 1, "node_id": "CR_kwDOAPAIsc8AAAABOUkpjg", "head_sha": "e886a61a6c91a6cdaaf7587b15192087b62570d8", "url": "https://api.github.com/repos/spack/spack/actions/jobs/5256063374", "html_url": "https://github.com/spack/spack/actions/runs/1867533284/jobs/2628983636", "status": "completed", "conclusion": "success", "started_at": "2022-02-19T02:42:10Z", "completed_at": "2022-02-19T02:46:15Z", "name": "unittests (2.7, clingo)", "steps": [{"name": "Set up job", "status": "completed", "conclusion": "success", "number": 1, "started_at": "2022-02-19T03:42:10.000+01:00", "completed_at": "2022-02-19T03:42:12.000+01:00"}, {"name": "Run actions/checkout@ec3a7ce113134d7a93b817d10a8272cb61118579", "status": "completed", "conclusion": "success", "number": 2, "started_at": "2022-02-19T03:42:12.000+01:00", "completed_at": "2022-02-19T03:42:32.000+01:00"}, {"name": "Run actions/setup-python@f38219332975fe8f9c04cca981d674bf22aea1d3", "status": "completed", "conclusion": "success", "number": 3, "started_at": "2022-02-19T03:42:32.000+01:00", "completed_at": "2022-02-19T03:42:32.000+01:00"}, {"name": "Install System packages", "status": "completed", "conclusion": "success", "number": 4, "started_at": "2022-02-19T03:42:32.000+01:00", "completed_at": "2022-02-19T03:42:51.000+01:00"}, {"name": "Install Python packages", "status": "completed", "conclusion": "success", "number": 5, "started_at": "2022-02-19T03:42:51.000+01:00", "completed_at": "2022-02-19T03:43:02.000+01:00"}, {"name": "Pin pathlib for Python 2.7", "status": "completed", "conclusion": "success", "number": 6, "started_at": "2022-02-19T03:43:02.000+01:00", "completed_at": "2022-02-19T03:43:03.000+01:00"}, {"name": "Setup git configuration", "status": "completed", "conclusion": "success", "number": 7, "started_at": "2022-02-19T03:43:03.000+01:00", "completed_at": "2022-02-19T03:43:03.000+01:00"}, {"name": "Bootstrap clingo", "status": "completed", "conclusion": "success", "number": 8, "started_at": "2022-02-19T03:43:03.000+01:00", "completed_at": "2022-02-19T03:43:42.000+01:00"}, {"name": "Run unit tests (full suite with coverage)", "status": "completed", "conclusion": "skipped", "number": 9, "started_at": "2022-02-19T03:43:42.000+01:00", "completed_at": "2022-02-19T03:43:42.000+01:00"}, {"name": "Run unit tests (reduced suite without coverage)", "status": "completed", "conclusion": "success", "number": 10, "started_at": "2022-02-19T03:43:42.000+01:00", "completed_at": "2022-02-19T03:46:15.000+01:00"}, {"name": "Run codecov/codecov-action@f32b3a3741e1053eb607407145bc9619351dc93b", "status": "completed", "conclusion": "skipped", "number": 11, "started_at": "2022-02-19T03:46:15.000+01:00", "completed_at": "2022-02-19T03:46:15.000+01:00"}, {"name": "Post Run actions/setup-python@f38219332975fe8f9c04cca981d674bf22aea1d3", "status": "completed", "conclusion": "success", "number": 21, "started_at": "2022-02-19T03:46:15.000+01:00", "completed_at": "2022-02-19T03:46:15.000+01:00"}, {"name": "Post Run actions/checkout@ec3a7ce113134d7a93b817d10a8272cb61118579", "status": "completed", "conclusion": "success", "number": 22, "started_at": "2022-02-19T03:46:15.000+01:00", "completed_at": "2022-02-19T03:46:15.000+01:00"}, {"name": "Complete job", "status": "completed", "conclusion": "success", "number": 23, "started_at": "2022-02-19T03:46:15.000+01:00", "completed_at": "2022-02-19T03:46:15.000+01:00"}], "check_run_url": "https://api.github.com/repos/spack/spack/check-runs/5256063374", "labels": ["ubuntu-latest"], "runner_id": 9, "runner_name": "GitHub Actions 9", "runner_group_id": 2, "runner_group_name": "GitHub Actions"}, {"id": 5256063393, "run_id": 1867533284, "run_url": "https://api.github.com/repos/spack/spack/actions/runs/1867533284", "run_attempt": 1, "node_id": "CR_kwDOAPAIsc8AAAABOUkpoQ", "head_sha": "e886a61a6c91a6cdaaf7587b15192087b62570d8", "url": "https://api.github.com/repos/spack/spack/actions/jobs/5256063393", "html_url": "https://github.com/spack/spack/actions/runs/1867533284/jobs/2628983652", "status": "completed", "conclusion": "success", "started_at": "2022-02-19T02:42:16Z", "completed_at": "2022-02-19T02:45:37Z", "name": "unittests (3.5, clingo)", "steps": [{"name": "Set up job", "status": "completed", "conclusion": "success", "number": 1, "started_at": "2022-02-19T03:42:16.000+01:00", "completed_at": "2022-02-19T03:42:17.000+01:00"}, {"name": "Run actions/checkout@ec3a7ce113134d7a93b817d10a8272cb61118579", "status": "completed", "conclusion": "success", "number": 2, "started_at": "2022-02-19T03:42:17.000+01:00", "completed_at": "2022-02-19T03:42:38.000+01:00"}, {"name": "Run actions/setup-python@f38219332975fe8f9c04cca981d674bf22aea1d3", "status": "completed", "conclusion": "success", "number": 3, "started_at": "2022-02-19T03:42:38.000+01:00", "completed_at": "2022-02-19T03:42:45.000+01:00"}, {"name": "Install System packages", "status": "completed", "conclusion": "success", "number": 4, "started_at": "2022-02-19T03:42:45.000+01:00", "completed_at": "2022-02-19T03:43:06.000+01:00"}, {"name": "Install Python packages", "status": "completed", "conclusion": "success", "number": 5, "started_at": "2022-02-19T03:43:06.000+01:00", "completed_at": "2022-02-19T03:43:13.000+01:00"}, {"name": "Pin pathlib for Python 2.7", "status": "completed", "conclusion": "skipped", "number": 6, "started_at": "2022-02-19T03:43:13.000+01:00", "completed_at": "2022-02-19T03:43:13.000+01:00"}, {"name": "Setup git configuration", "status": "completed", "conclusion": "success", "number": 7, "started_at": "2022-02-19T03:43:13.000+01:00", "completed_at": "2022-02-19T03:43:13.000+01:00"}, {"name": "Bootstrap clingo", "status": "completed", "conclusion": "success", "number": 8, "started_at": "2022-02-19T03:43:13.000+01:00", "completed_at": "2022-02-19T03:43:57.000+01:00"}, {"name": "Run unit tests (full suite with coverage)", "status": "completed", "conclusion": "skipped", "number": 9, "started_at": "2022-02-19T03:43:57.000+01:00", "completed_at": "2022-02-19T03:43:57.000+01:00"}, {"name": "Run unit tests (reduced suite without coverage)", "status": "completed", "conclusion": "success", "number": 10, "started_at": "2022-02-19T03:43:57.000+01:00", "completed_at": "2022-02-19T03:45:36.000+01:00"}, {"name": "Run codecov/codecov-action@f32b3a3741e1053eb607407145bc9619351dc93b", "status": "completed", "conclusion": "skipped", "number": 11, "started_at": "2022-02-19T03:45:36.000+01:00", "completed_at": "2022-02-19T03:45:36.000+01:00"}, {"name": "Post Run actions/setup-python@f38219332975fe8f9c04cca981d674bf22aea1d3", "status": "completed", "conclusion": "success", "number": 21, "started_at": "2022-02-19T03:45:36.000+01:00", "completed_at": "2022-02-19T03:45:37.000+01:00"}, {"name": "Post Run actions/checkout@ec3a7ce113134d7a93b817d10a8272cb61118579", "status": "completed", "conclusion": "success", "number": 22, "started_at": "2022-02-19T03:45:37.000+01:00", "completed_at": "2022-02-19T03:45:37.000+01:00"}, {"name": "Complete job", "status": "completed", "conclusion": "success", "number": 23, "started_at": "2022-02-19T03:45:37.000+01:00", "completed_at": "2022-02-19T03:45:37.000+01:00"}], "check_run_url": "https://api.github.com/repos/spack/spack/check-runs/5256063393", "labels": ["ubuntu-latest"], "runner_id": 14, "runner_name": "GitHub Actions 14", "runner_group_id": 2, "runner_group_name": "GitHub Actions"}, {"id": 5256063408, "run_id": 1867533284, "run_url": "https://api.github.com/repos/spack/spack/actions/runs/1867533284", "run_attempt": 1, "node_id": "CR_kwDOAPAIsc8AAAABOUkpsA", "head_sha": "e886a61a6c91a6cdaaf7587b15192087b62570d8", "url": "https://api.github.com/repos/spack/spack/actions/jobs/5256063408", "html_url": "https://github.com/spack/spack/actions/runs/1867533284/jobs/2628983666", "status": "completed", "conclusion": "success", "started_at": "2022-02-19T02:42:17Z", "completed_at": "2022-02-19T02:45:30Z", "name": "unittests (3.6, clingo)", "steps": [{"name": "Set up job", "status": "completed", "conclusion": "success", "number": 1, "started_at": "2022-02-19T03:42:17.000+01:00", "completed_at": "2022-02-19T03:42:19.000+01:00"}, {"name": "Run actions/checkout@ec3a7ce113134d7a93b817d10a8272cb61118579", "status": "completed", "conclusion": "success", "number": 2, "started_at": "2022-02-19T03:42:19.000+01:00", "completed_at": "2022-02-19T03:42:37.000+01:00"}, {"name": "Run actions/setup-python@f38219332975fe8f9c04cca981d674bf22aea1d3", "status": "completed", "conclusion": "success", "number": 3, "started_at": "2022-02-19T03:42:37.000+01:00", "completed_at": "2022-02-19T03:42:37.000+01:00"}, {"name": "Install System packages", "status": "completed", "conclusion": "success", "number": 4, "started_at": "2022-02-19T03:42:37.000+01:00", "completed_at": "2022-02-19T03:43:02.000+01:00"}, {"name": "Install Python packages", "status": "completed", "conclusion": "success", "number": 5, "started_at": "2022-02-19T03:43:02.000+01:00", "completed_at": "2022-02-19T03:43:15.000+01:00"}, {"name": "Pin pathlib for Python 2.7", "status": "completed", "conclusion": "skipped", "number": 6, "started_at": "2022-02-19T03:43:15.000+01:00", "completed_at": "2022-02-19T03:43:15.000+01:00"}, {"name": "Setup git configuration", "status": "completed", "conclusion": "success", "number": 7, "started_at": "2022-02-19T03:43:15.000+01:00", "completed_at": "2022-02-19T03:43:15.000+01:00"}, {"name": "Bootstrap clingo", "status": "completed", "conclusion": "success", "number": 8, "started_at": "2022-02-19T03:43:15.000+01:00", "completed_at": "2022-02-19T03:43:58.000+01:00"}, {"name": "Run unit tests (full suite with coverage)", "status": "completed", "conclusion": "skipped", "number": 9, "started_at": "2022-02-19T03:43:58.000+01:00", "completed_at": "2022-02-19T03:43:58.000+01:00"}, {"name": "Run unit tests (reduced suite without coverage)", "status": "completed", "conclusion": "success", "number": 10, "started_at": "2022-02-19T03:43:58.000+01:00", "completed_at": "2022-02-19T03:45:30.000+01:00"}, {"name": "Run codecov/codecov-action@f32b3a3741e1053eb607407145bc9619351dc93b", "status": "completed", "conclusion": "skipped", "number": 11, "started_at": "2022-02-19T03:45:30.000+01:00", "completed_at": "2022-02-19T03:45:30.000+01:00"}, {"name": "Post Run actions/setup-python@f38219332975fe8f9c04cca981d674bf22aea1d3", "status": "completed", "conclusion": "success", "number": 21, "started_at": "2022-02-19T03:45:30.000+01:00", "completed_at": "2022-02-19T03:45:30.000+01:00"}, {"name": "Post Run actions/checkout@ec3a7ce113134d7a93b817d10a8272cb61118579", "status": "completed", "conclusion": "success", "number": 22, "started_at": "2022-02-19T03:45:30.000+01:00", "completed_at": "2022-02-19T03:45:30.000+01:00"}, {"name": "Complete job", "status": "completed", "conclusion": "success", "number": 23, "started_at": "2022-02-19T03:45:30.000+01:00", "completed_at": "2022-02-19T03:45:30.000+01:00"}], "check_run_url": "https://api.github.com/repos/spack/spack/check-runs/5256063408", "labels": ["ubuntu-latest"], "runner_id": 10, "runner_name": "GitHub Actions 10", "runner_group_id": 2, "runner_group_name": "GitHub Actions"}, {"id": 5256063424, "run_id": 1867533284, "run_url": "https://api.github.com/repos/spack/spack/actions/runs/1867533284", "run_attempt": 1, "node_id": "CR_kwDOAPAIsc8AAAABOUkpwA", "head_sha": "e886a61a6c91a6cdaaf7587b15192087b62570d8", "url": "https://api.github.com/repos/spack/spack/actions/jobs/5256063424", "html_url": "https://github.com/spack/spack/actions/runs/1867533284/jobs/2628983678", "status": "completed", "conclusion": "success", "started_at": "2022-02-19T02:42:20Z", "completed_at": "2022-02-19T02:45:11Z", "name": "unittests (3.7, clingo)", "steps": [{"name": "Set up job", "status": "completed", "conclusion": "success", "number": 1, "started_at": "2022-02-19T03:42:20.000+01:00", "completed_at": "2022-02-19T03:42:22.000+01:00"}, {"name": "Run actions/checkout@ec3a7ce113134d7a93b817d10a8272cb61118579", "status": "completed", "conclusion": "success", "number": 2, "started_at": "2022-02-19T03:42:22.000+01:00", "completed_at": "2022-02-19T03:42:40.000+01:00"}, {"name": "Run actions/setup-python@f38219332975fe8f9c04cca981d674bf22aea1d3", "status": "completed", "conclusion": "success", "number": 3, "started_at": "2022-02-19T03:42:40.000+01:00", "completed_at": "2022-02-19T03:42:40.000+01:00"}, {"name": "Install System packages", "status": "completed", "conclusion": "success", "number": 4, "started_at": "2022-02-19T03:42:40.000+01:00", "completed_at": "2022-02-19T03:42:58.000+01:00"}, {"name": "Install Python packages", "status": "completed", "conclusion": "success", "number": 5, "started_at": "2022-02-19T03:42:58.000+01:00", "completed_at": "2022-02-19T03:43:07.000+01:00"}, {"name": "Pin pathlib for Python 2.7", "status": "completed", "conclusion": "skipped", "number": 6, "started_at": "2022-02-19T03:43:07.000+01:00", "completed_at": "2022-02-19T03:43:07.000+01:00"}, {"name": "Setup git configuration", "status": "completed", "conclusion": "success", "number": 7, "started_at": "2022-02-19T03:43:07.000+01:00", "completed_at": "2022-02-19T03:43:07.000+01:00"}, {"name": "Bootstrap clingo", "status": "completed", "conclusion": "success", "number": 8, "started_at": "2022-02-19T03:43:07.000+01:00", "completed_at": "2022-02-19T03:43:45.000+01:00"}, {"name": "Run unit tests (full suite with coverage)", "status": "completed", "conclusion": "skipped", "number": 9, "started_at": "2022-02-19T03:43:45.000+01:00", "completed_at": "2022-02-19T03:43:45.000+01:00"}, {"name": "Run unit tests (reduced suite without coverage)", "status": "completed", "conclusion": "success", "number": 10, "started_at": "2022-02-19T03:43:45.000+01:00", "completed_at": "2022-02-19T03:45:11.000+01:00"}, {"name": "Run codecov/codecov-action@f32b3a3741e1053eb607407145bc9619351dc93b", "status": "completed", "conclusion": "skipped", "number": 11, "started_at": "2022-02-19T03:45:11.000+01:00", "completed_at": "2022-02-19T03:45:11.000+01:00"}, {"name": "Post Run actions/setup-python@f38219332975fe8f9c04cca981d674bf22aea1d3", "status": "completed", "conclusion": "success", "number": 21, "started_at": "2022-02-19T03:45:11.000+01:00", "completed_at": "2022-02-19T03:45:11.000+01:00"}, {"name": "Post Run actions/checkout@ec3a7ce113134d7a93b817d10a8272cb61118579", "status": "completed", "conclusion": "success", "number": 22, "started_at": "2022-02-19T03:45:11.000+01:00", "completed_at": "2022-02-19T03:45:11.000+01:00"}, {"name": "Complete job", "status": "completed", "conclusion": "success", "number": 23, "started_at": "2022-02-19T03:45:11.000+01:00", "completed_at": "2022-02-19T03:45:11.000+01:00"}], "check_run_url": "https://api.github.com/repos/spack/spack/check-runs/5256063424", "labels": ["ubuntu-latest"], "runner_id": 11, "runner_name": "GitHub Actions 11", "runner_group_id": 2, "runner_group_name": "GitHub Actions"}, {"id": 5256063446, "run_id": 1867533284, "run_url": "https://api.github.com/repos/spack/spack/actions/runs/1867533284", "run_attempt": 1, "node_id": "CR_kwDOAPAIsc8AAAABOUkp1g", "head_sha": "e886a61a6c91a6cdaaf7587b15192087b62570d8", "url": "https://api.github.com/repos/spack/spack/actions/jobs/5256063446", "html_url": "https://github.com/spack/spack/actions/runs/1867533284/jobs/2628983693", "status": "completed", "conclusion": "success", "started_at": "2022-02-19T02:42:49Z", "completed_at": "2022-02-19T02:45:43Z", "name": "unittests (3.8, clingo)", "steps": [{"name": "Set up job", "status": "completed", "conclusion": "success", "number": 1, "started_at": "2022-02-19T03:42:49.000+01:00", "completed_at": "2022-02-19T03:42:51.000+01:00"}, {"name": "Run actions/checkout@ec3a7ce113134d7a93b817d10a8272cb61118579", "status": "completed", "conclusion": "success", "number": 2, "started_at": "2022-02-19T03:42:51.000+01:00", "completed_at": "2022-02-19T03:43:14.000+01:00"}, {"name": "Run actions/setup-python@f38219332975fe8f9c04cca981d674bf22aea1d3", "status": "completed", "conclusion": "success", "number": 3, "started_at": "2022-02-19T03:43:14.000+01:00", "completed_at": "2022-02-19T03:43:14.000+01:00"}, {"name": "Install System packages", "status": "completed", "conclusion": "success", "number": 4, "started_at": "2022-02-19T03:43:14.000+01:00", "completed_at": "2022-02-19T03:43:30.000+01:00"}, {"name": "Install Python packages", "status": "completed", "conclusion": "success", "number": 5, "started_at": "2022-02-19T03:43:30.000+01:00", "completed_at": "2022-02-19T03:43:38.000+01:00"}, {"name": "Pin pathlib for Python 2.7", "status": "completed", "conclusion": "skipped", "number": 6, "started_at": "2022-02-19T03:43:38.000+01:00", "completed_at": "2022-02-19T03:43:38.000+01:00"}, {"name": "Setup git configuration", "status": "completed", "conclusion": "success", "number": 7, "started_at": "2022-02-19T03:43:38.000+01:00", "completed_at": "2022-02-19T03:43:38.000+01:00"}, {"name": "Bootstrap clingo", "status": "completed", "conclusion": "success", "number": 8, "started_at": "2022-02-19T03:43:38.000+01:00", "completed_at": "2022-02-19T03:44:17.000+01:00"}, {"name": "Run unit tests (full suite with coverage)", "status": "completed", "conclusion": "skipped", "number": 9, "started_at": "2022-02-19T03:44:17.000+01:00", "completed_at": "2022-02-19T03:44:17.000+01:00"}, {"name": "Run unit tests (reduced suite without coverage)", "status": "completed", "conclusion": "success", "number": 10, "started_at": "2022-02-19T03:44:17.000+01:00", "completed_at": "2022-02-19T03:45:43.000+01:00"}, {"name": "Run codecov/codecov-action@f32b3a3741e1053eb607407145bc9619351dc93b", "status": "completed", "conclusion": "skipped", "number": 11, "started_at": "2022-02-19T03:45:43.000+01:00", "completed_at": "2022-02-19T03:45:43.000+01:00"}, {"name": "Post Run actions/setup-python@f38219332975fe8f9c04cca981d674bf22aea1d3", "status": "completed", "conclusion": "success", "number": 21, "started_at": "2022-02-19T03:45:43.000+01:00", "completed_at": "2022-02-19T03:45:43.000+01:00"}, {"name": "Post Run actions/checkout@ec3a7ce113134d7a93b817d10a8272cb61118579", "status": "completed", "conclusion": "success", "number": 22, "started_at": "2022-02-19T03:45:43.000+01:00", "completed_at": "2022-02-19T03:45:43.000+01:00"}, {"name": "Complete job", "status": "completed", "conclusion": "success", "number": 23, "started_at": "2022-02-19T03:45:43.000+01:00", "completed_at": "2022-02-19T03:45:43.000+01:00"}], "check_run_url": "https://api.github.com/repos/spack/spack/check-runs/5256063446", "labels": ["ubuntu-latest"], "runner_id": 19, "runner_name": "GitHub Actions 19", "runner_group_id": 2, "runner_group_name": "GitHub Actions"}, {"id": 5256063467, "run_id": 1867533284, "run_url": "https://api.github.com/repos/spack/spack/actions/runs/1867533284", "run_attempt": 1, "node_id": "CR_kwDOAPAIsc8AAAABOUkp6w", "head_sha": "e886a61a6c91a6cdaaf7587b15192087b62570d8", "url": "https://api.github.com/repos/spack/spack/actions/jobs/5256063467", "html_url": "https://github.com/spack/spack/actions/runs/1867533284/jobs/2628983708", "status": "completed", "conclusion": "success", "started_at": "2022-02-19T02:42:30Z", "completed_at": "2022-02-19T02:45:25Z", "name": "unittests (3.9, clingo)", "steps": [{"name": "Set up job", "status": "completed", "conclusion": "success", "number": 1, "started_at": "2022-02-19T03:42:30.000+01:00", "completed_at": "2022-02-19T03:42:32.000+01:00"}, {"name": "Run actions/checkout@ec3a7ce113134d7a93b817d10a8272cb61118579", "status": "completed", "conclusion": "success", "number": 2, "started_at": "2022-02-19T03:42:32.000+01:00", "completed_at": "2022-02-19T03:42:50.000+01:00"}, {"name": "Run actions/setup-python@f38219332975fe8f9c04cca981d674bf22aea1d3", "status": "completed", "conclusion": "success", "number": 3, "started_at": "2022-02-19T03:42:50.000+01:00", "completed_at": "2022-02-19T03:42:51.000+01:00"}, {"name": "Install System packages", "status": "completed", "conclusion": "success", "number": 4, "started_at": "2022-02-19T03:42:51.000+01:00", "completed_at": "2022-02-19T03:43:07.000+01:00"}, {"name": "Install Python packages", "status": "completed", "conclusion": "success", "number": 5, "started_at": "2022-02-19T03:43:07.000+01:00", "completed_at": "2022-02-19T03:43:18.000+01:00"}, {"name": "Pin pathlib for Python 2.7", "status": "completed", "conclusion": "skipped", "number": 6, "started_at": "2022-02-19T03:43:18.000+01:00", "completed_at": "2022-02-19T03:43:18.000+01:00"}, {"name": "Setup git configuration", "status": "completed", "conclusion": "success", "number": 7, "started_at": "2022-02-19T03:43:18.000+01:00", "completed_at": "2022-02-19T03:43:18.000+01:00"}, {"name": "Bootstrap clingo", "status": "completed", "conclusion": "success", "number": 8, "started_at": "2022-02-19T03:43:18.000+01:00", "completed_at": "2022-02-19T03:43:59.000+01:00"}, {"name": "Run unit tests (full suite with coverage)", "status": "completed", "conclusion": "skipped", "number": 9, "started_at": "2022-02-19T03:43:59.000+01:00", "completed_at": "2022-02-19T03:43:59.000+01:00"}, {"name": "Run unit tests (reduced suite without coverage)", "status": "completed", "conclusion": "success", "number": 10, "started_at": "2022-02-19T03:43:59.000+01:00", "completed_at": "2022-02-19T03:45:24.000+01:00"}, {"name": "Run codecov/codecov-action@f32b3a3741e1053eb607407145bc9619351dc93b", "status": "completed", "conclusion": "skipped", "number": 11, "started_at": "2022-02-19T03:45:24.000+01:00", "completed_at": "2022-02-19T03:45:24.000+01:00"}, {"name": "Post Run actions/setup-python@f38219332975fe8f9c04cca981d674bf22aea1d3", "status": "completed", "conclusion": "success", "number": 21, "started_at": "2022-02-19T03:45:24.000+01:00", "completed_at": "2022-02-19T03:45:24.000+01:00"}, {"name": "Post Run actions/checkout@ec3a7ce113134d7a93b817d10a8272cb61118579", "status": "completed", "conclusion": "success", "number": 22, "started_at": "2022-02-19T03:45:24.000+01:00", "completed_at": "2022-02-19T03:45:24.000+01:00"}, {"name": "Complete job", "status": "completed", "conclusion": "success", "number": 23, "started_at": "2022-02-19T03:45:24.000+01:00", "completed_at": "2022-02-19T03:45:25.000+01:00"}], "check_run_url": "https://api.github.com/repos/spack/spack/check-runs/5256063467", "labels": ["ubuntu-latest"], "runner_id": 13, "runner_name": "GitHub Actions 13", "runner_group_id": 2, "runner_group_name": "GitHub Actions"}, {"id": 5256063504, "run_id": 1867533284, "run_url": "https://api.github.com/repos/spack/spack/actions/runs/1867533284", "run_attempt": 1, "node_id": "CR_kwDOAPAIsc8AAAABOUkqEA", "head_sha": "e886a61a6c91a6cdaaf7587b15192087b62570d8", "url": "https://api.github.com/repos/spack/spack/actions/jobs/5256063504", "html_url": "https://github.com/spack/spack/actions/runs/1867533284/jobs/2628983737", "status": "completed", "conclusion": "success", "started_at": "2022-02-19T02:42:16Z", "completed_at": "2022-02-19T02:46:32Z", "name": "unittests (2.7, original)", "steps": [{"name": "Set up job", "status": "completed", "conclusion": "success", "number": 1, "started_at": "2022-02-19T03:42:16.000+01:00", "completed_at": "2022-02-19T03:42:19.000+01:00"}, {"name": "Run actions/checkout@ec3a7ce113134d7a93b817d10a8272cb61118579", "status": "completed", "conclusion": "success", "number": 2, "started_at": "2022-02-19T03:42:19.000+01:00", "completed_at": "2022-02-19T03:42:37.000+01:00"}, {"name": "Run actions/setup-python@f38219332975fe8f9c04cca981d674bf22aea1d3", "status": "completed", "conclusion": "success", "number": 3, "started_at": "2022-02-19T03:42:37.000+01:00", "completed_at": "2022-02-19T03:42:37.000+01:00"}, {"name": "Install System packages", "status": "completed", "conclusion": "success", "number": 4, "started_at": "2022-02-19T03:42:37.000+01:00", "completed_at": "2022-02-19T03:42:54.000+01:00"}, {"name": "Install Python packages", "status": "completed", "conclusion": "success", "number": 5, "started_at": "2022-02-19T03:42:54.000+01:00", "completed_at": "2022-02-19T03:43:05.000+01:00"}, {"name": "Pin pathlib for Python 2.7", "status": "completed", "conclusion": "success", "number": 6, "started_at": "2022-02-19T03:43:05.000+01:00", "completed_at": "2022-02-19T03:43:06.000+01:00"}, {"name": "Setup git configuration", "status": "completed", "conclusion": "success", "number": 7, "started_at": "2022-02-19T03:43:06.000+01:00", "completed_at": "2022-02-19T03:43:06.000+01:00"}, {"name": "Bootstrap clingo", "status": "completed", "conclusion": "skipped", "number": 8, "started_at": "2022-02-19T03:43:06.000+01:00", "completed_at": "2022-02-19T03:43:06.000+01:00"}, {"name": "Run unit tests (full suite with coverage)", "status": "completed", "conclusion": "skipped", "number": 9, "started_at": "2022-02-19T03:43:06.000+01:00", "completed_at": "2022-02-19T03:43:06.000+01:00"}, {"name": "Run unit tests (reduced suite without coverage)", "status": "completed", "conclusion": "success", "number": 10, "started_at": "2022-02-19T03:43:06.000+01:00", "completed_at": "2022-02-19T03:46:31.000+01:00"}, {"name": "Run codecov/codecov-action@f32b3a3741e1053eb607407145bc9619351dc93b", "status": "completed", "conclusion": "skipped", "number": 11, "started_at": "2022-02-19T03:46:31.000+01:00", "completed_at": "2022-02-19T03:46:31.000+01:00"}, {"name": "Post Run actions/setup-python@f38219332975fe8f9c04cca981d674bf22aea1d3", "status": "completed", "conclusion": "success", "number": 21, "started_at": "2022-02-19T03:46:31.000+01:00", "completed_at": "2022-02-19T03:46:31.000+01:00"}, {"name": "Post Run actions/checkout@ec3a7ce113134d7a93b817d10a8272cb61118579", "status": "completed", "conclusion": "success", "number": 22, "started_at": "2022-02-19T03:46:31.000+01:00", "completed_at": "2022-02-19T03:46:31.000+01:00"}, {"name": "Complete job", "status": "completed", "conclusion": "success", "number": 23, "started_at": "2022-02-19T03:46:31.000+01:00", "completed_at": "2022-02-19T03:46:32.000+01:00"}], "check_run_url": "https://api.github.com/repos/spack/spack/check-runs/5256063504", "labels": ["ubuntu-latest"], "runner_id": 12, "runner_name": "GitHub Actions 12", "runner_group_id": 2, "runner_group_name": "GitHub Actions"}, {"id": 5256063526, "run_id": 1867533284, "run_url": "https://api.github.com/repos/spack/spack/actions/runs/1867533284", "run_attempt": 1, "node_id": "CR_kwDOAPAIsc8AAAABOUkqJg", "head_sha": "e886a61a6c91a6cdaaf7587b15192087b62570d8", "url": "https://api.github.com/repos/spack/spack/actions/jobs/5256063526", "html_url": "https://github.com/spack/spack/actions/runs/1867533284/jobs/2628983757", "status": "completed", "conclusion": "success", "started_at": "2022-02-19T02:42:18Z", "completed_at": "2022-02-19T02:46:03Z", "name": "unittests (3.6, original)", "steps": [{"name": "Set up job", "status": "completed", "conclusion": "success", "number": 1, "started_at": "2022-02-19T03:42:18.000+01:00", "completed_at": "2022-02-19T03:42:19.000+01:00"}, {"name": "Run actions/checkout@ec3a7ce113134d7a93b817d10a8272cb61118579", "status": "completed", "conclusion": "success", "number": 2, "started_at": "2022-02-19T03:42:19.000+01:00", "completed_at": "2022-02-19T03:42:40.000+01:00"}, {"name": "Run actions/setup-python@f38219332975fe8f9c04cca981d674bf22aea1d3", "status": "completed", "conclusion": "success", "number": 3, "started_at": "2022-02-19T03:42:40.000+01:00", "completed_at": "2022-02-19T03:42:40.000+01:00"}, {"name": "Install System packages", "status": "completed", "conclusion": "success", "number": 4, "started_at": "2022-02-19T03:42:40.000+01:00", "completed_at": "2022-02-19T03:43:00.000+01:00"}, {"name": "Install Python packages", "status": "completed", "conclusion": "success", "number": 5, "started_at": "2022-02-19T03:43:00.000+01:00", "completed_at": "2022-02-19T03:43:14.000+01:00"}, {"name": "Pin pathlib for Python 2.7", "status": "completed", "conclusion": "skipped", "number": 6, "started_at": "2022-02-19T03:43:14.000+01:00", "completed_at": "2022-02-19T03:43:14.000+01:00"}, {"name": "Setup git configuration", "status": "completed", "conclusion": "success", "number": 7, "started_at": "2022-02-19T03:43:14.000+01:00", "completed_at": "2022-02-19T03:43:14.000+01:00"}, {"name": "Bootstrap clingo", "status": "completed", "conclusion": "skipped", "number": 8, "started_at": "2022-02-19T03:43:14.000+01:00", "completed_at": "2022-02-19T03:43:14.000+01:00"}, {"name": "Run unit tests (full suite with coverage)", "status": "completed", "conclusion": "skipped", "number": 9, "started_at": "2022-02-19T03:43:14.000+01:00", "completed_at": "2022-02-19T03:43:14.000+01:00"}, {"name": "Run unit tests (reduced suite without coverage)", "status": "completed", "conclusion": "success", "number": 10, "started_at": "2022-02-19T03:43:14.000+01:00", "completed_at": "2022-02-19T03:46:03.000+01:00"}, {"name": "Run codecov/codecov-action@f32b3a3741e1053eb607407145bc9619351dc93b", "status": "completed", "conclusion": "skipped", "number": 11, "started_at": "2022-02-19T03:46:03.000+01:00", "completed_at": "2022-02-19T03:46:03.000+01:00"}, {"name": "Post Run actions/setup-python@f38219332975fe8f9c04cca981d674bf22aea1d3", "status": "completed", "conclusion": "success", "number": 21, "started_at": "2022-02-19T03:46:03.000+01:00", "completed_at": "2022-02-19T03:46:03.000+01:00"}, {"name": "Post Run actions/checkout@ec3a7ce113134d7a93b817d10a8272cb61118579", "status": "completed", "conclusion": "success", "number": 22, "started_at": "2022-02-19T03:46:03.000+01:00", "completed_at": "2022-02-19T03:46:03.000+01:00"}, {"name": "Complete job", "status": "completed", "conclusion": "success", "number": 23, "started_at": "2022-02-19T03:46:03.000+01:00", "completed_at": "2022-02-19T03:46:03.000+01:00"}], "check_run_url": "https://api.github.com/repos/spack/spack/check-runs/5256063526", "labels": ["ubuntu-latest"], "runner_id": 17, "runner_name": "GitHub Actions 17", "runner_group_id": 2, "runner_group_name": "GitHub Actions"}, {"id": 5256063548, "run_id": 1867533284, "run_url": "https://api.github.com/repos/spack/spack/actions/runs/1867533284", "run_attempt": 1, "node_id": "CR_kwDOAPAIsc8AAAABOUkqPA", "head_sha": "e886a61a6c91a6cdaaf7587b15192087b62570d8", "url": "https://api.github.com/repos/spack/spack/actions/jobs/5256063548", "html_url": "https://github.com/spack/spack/actions/runs/1867533284/jobs/2628983774", "status": "completed", "conclusion": "success", "started_at": "2022-02-19T02:42:47Z", "completed_at": "2022-02-19T02:46:49Z", "name": "unittests (3.9, original)", "steps": [{"name": "Set up job", "status": "completed", "conclusion": "success", "number": 1, "started_at": "2022-02-19T03:42:47.000+01:00", "completed_at": "2022-02-19T03:42:49.000+01:00"}, {"name": "Run actions/checkout@ec3a7ce113134d7a93b817d10a8272cb61118579", "status": "completed", "conclusion": "success", "number": 2, "started_at": "2022-02-19T03:42:49.000+01:00", "completed_at": "2022-02-19T03:43:12.000+01:00"}, {"name": "Run actions/setup-python@f38219332975fe8f9c04cca981d674bf22aea1d3", "status": "completed", "conclusion": "success", "number": 3, "started_at": "2022-02-19T03:43:12.000+01:00", "completed_at": "2022-02-19T03:43:12.000+01:00"}, {"name": "Install System packages", "status": "completed", "conclusion": "success", "number": 4, "started_at": "2022-02-19T03:43:12.000+01:00", "completed_at": "2022-02-19T03:43:34.000+01:00"}, {"name": "Install Python packages", "status": "completed", "conclusion": "success", "number": 5, "started_at": "2022-02-19T03:43:34.000+01:00", "completed_at": "2022-02-19T03:43:45.000+01:00"}, {"name": "Pin pathlib for Python 2.7", "status": "completed", "conclusion": "skipped", "number": 6, "started_at": "2022-02-19T03:43:45.000+01:00", "completed_at": "2022-02-19T03:43:45.000+01:00"}, {"name": "Setup git configuration", "status": "completed", "conclusion": "success", "number": 7, "started_at": "2022-02-19T03:43:45.000+01:00", "completed_at": "2022-02-19T03:43:45.000+01:00"}, {"name": "Bootstrap clingo", "status": "completed", "conclusion": "skipped", "number": 8, "started_at": "2022-02-19T03:43:45.000+01:00", "completed_at": "2022-02-19T03:43:45.000+01:00"}, {"name": "Run unit tests (full suite with coverage)", "status": "completed", "conclusion": "skipped", "number": 9, "started_at": "2022-02-19T03:43:45.000+01:00", "completed_at": "2022-02-19T03:43:45.000+01:00"}, {"name": "Run unit tests (reduced suite without coverage)", "status": "completed", "conclusion": "success", "number": 10, "started_at": "2022-02-19T03:43:45.000+01:00", "completed_at": "2022-02-19T03:46:48.000+01:00"}, {"name": "Run codecov/codecov-action@f32b3a3741e1053eb607407145bc9619351dc93b", "status": "completed", "conclusion": "skipped", "number": 11, "started_at": "2022-02-19T03:46:48.000+01:00", "completed_at": "2022-02-19T03:46:48.000+01:00"}, {"name": "Post Run actions/setup-python@f38219332975fe8f9c04cca981d674bf22aea1d3", "status": "completed", "conclusion": "success", "number": 21, "started_at": "2022-02-19T03:46:48.000+01:00", "completed_at": "2022-02-19T03:46:49.000+01:00"}, {"name": "Post Run actions/checkout@ec3a7ce113134d7a93b817d10a8272cb61118579", "status": "completed", "conclusion": "success", "number": 22, "started_at": "2022-02-19T03:46:49.000+01:00", "completed_at": "2022-02-19T03:46:49.000+01:00"}, {"name": "Complete job", "status": "completed", "conclusion": "success", "number": 23, "started_at": "2022-02-19T03:46:49.000+01:00", "completed_at": "2022-02-19T03:46:49.000+01:00"}], "check_run_url": "https://api.github.com/repos/spack/spack/check-runs/5256063548", "labels": ["ubuntu-latest"], "runner_id": 15, "runner_name": "GitHub Actions 15", "runner_group_id": 2, "runner_group_name": "GitHub Actions"}]}