{"total_count": 36, "jobs": [{"id": 9074936157, "run_id": 3314691390, "run_url": "https://api.github.com/repos/spack/spack/actions/runs/3314691390", "run_attempt": 1, "node_id": "CR_kwDOAPAIsc8AAAACHOiJXQ", "head_sha": "0b971a1aef2fa27574d3c7c5f1a8a2eed6c2c1ec", "url": "https://api.github.com/repos/spack/spack/actions/jobs/9074936157", "html_url": "https://github.com/spack/spack/actions/runs/3314691390/jobs/5474307626", "status": "completed", "conclusion": "success", "started_at": "2022-10-24T17:38:03Z", "completed_at": "2022-10-24T17:38:48Z", "name": "changes", "steps": [{"name": "Set up job", "status": "completed", "conclusion": "success", "number": 1, "started_at": "2022-10-24T19:38:03.000+02:00", "completed_at": "2022-10-24T19:38:05.000+02:00"}, {"name": "Run actions/checkout@93ea575cb5d8a053eaa0ac8fa3b40d7e05a33cc8", "status": "completed", "conclusion": "success", "number": 2, "started_at": "2022-10-24T19:38:05.000+02:00", "completed_at": "2022-10-24T19:38:46.000+02:00"}, {"name": "Run dorny/paths-filter@b2feaf19c27470162a626bd6fa8438ae5b263721", "status": "completed", "conclusion": "success", "number": 3, "started_at": "2022-10-24T19:38:46.000+02:00", "completed_at": "2022-10-24T19:38:46.000+02:00"}, {"name": "Post Run actions/checkout@93ea575cb5d8a053eaa0ac8fa3b40d7e05a33cc8", "status": "completed", "conclusion": "success", "number": 6, "started_at": "2022-10-24T19:38:48.000+02:00", "completed_at": "2022-10-24T19:38:48.000+02:00"}, {"name": "Complete job", "status": "completed", "conclusion": "success", "number": 7, "started_at": "2022-10-24T19:38:46.000+02:00", "completed_at": "2022-10-24T19:38:46.000+02:00"}], "check_run_url": "https://api.github.com/repos/spack/spack/check-runs/9074936157", "labels": ["ubuntu-latest"], "runner_id": 15, "runner_name": "GitHub Actions 15", "runner_group_id": 2, "runner_group_name": "GitHub Actions"}, {"id": 9075501450, "run_id": 3314691390, "run_url": "https://api.github.com/repos/spack/spack/actions/runs/3314691390", "run_attempt": 1, "node_id": "CR_kwDOAPAIsc8AAAACHPEpig", "head_sha": "0b971a1aef2fa27574d3c7c5f1a8a2eed6c2c1ec", "url": "https://api.github.com/repos/spack/spack/actions/jobs/9075501450", "html_url": "https://github.com/spack/spack/actions/runs/3314691390/jobs/5474724117", "status": "completed", "conclusion": "success", "started_at": "2022-10-24T17:45:14Z", "completed_at": "2022-10-24T17:45:57Z", "name": "prechecks / validate", "steps": [{"name": "Set up job", "status": "completed", "conclusion": "success", "number": 1, "started_at": "2022-10-24T19:45:14.000+02:00", "completed_at": "2022-10-24T19:45:15.000+02:00"}, {"name": "Run actions/checkout@93ea575cb5d8a053eaa0ac8fa3b40d7e05a33cc8", "status": "completed", "conclusion": "success", "number": 2, "started_at": "2022-10-24T19:45:15.000+02:00", "completed_at": "2022-10-24T19:45:19.000+02:00"}, {"name": "Run actions/setup-python@13ae5bb136fac2878aff31522b9efb785519f984", "status": "completed", "conclusion": "success", "number": 3, "started_at": "2022-10-24T19:45:19.000+02:00", "completed_at": "2022-10-24T19:45:23.000+02:00"}, {"name": "Install Python Packages", "status": "completed", "conclusion": "success", "number": 4, "started_at": "2022-10-24T19:45:23.000+02:00", "completed_at": "2022-10-24T19:45:25.000+02:00"}, {"name": "vermin (Spack's Core)", "status": "completed", "conclusion": "success", "number": 5, "started_at": "2022-10-24T19:45:25.000+02:00", "completed_at": "2022-10-24T19:45:33.000+02:00"}, {"name": "vermin (Repositories)", "status": "completed", "conclusion": "success", "number": 6, "started_at": "2022-10-24T19:45:33.000+02:00", "completed_at": "2022-10-24T19:45:55.000+02:00"}, {"name": "Post Run actions/setup-python@13ae5bb136fac2878aff31522b9efb785519f984", "status": "completed", "conclusion": "success", "number": 11, "started_at": "2022-10-24T19:45:56.000+02:00", "completed_at": "2022-10-24T19:45:56.000+02:00"}, {"name": "Post Run actions/checkout@93ea575cb5d8a053eaa0ac8fa3b40d7e05a33cc8", "status": "completed", "conclusion": "success", "number": 12, "started_at": "2022-10-24T19:45:56.000+02:00", "completed_at": "2022-10-24T19:45:56.000+02:00"}, {"name": "Complete job", "status": "completed", "conclusion": "success", "number": 13, "started_at": "2022-10-24T19:45:56.000+02:00", "completed_at": "2022-10-24T19:45:56.000+02:00"}], "check_run_url": "https://api.github.com/repos/spack/spack/check-runs/9075501450", "labels": ["ubuntu-latest"], "runner_id": 8, "runner_name": "GitHub Actions 8", "runner_group_id": 2, "runner_group_name": "GitHub Actions"}, {"id": 9075501623, "run_id": 3314691390, "run_url": "https://api.github.com/repos/spack/spack/actions/runs/3314691390", "run_attempt": 1, "node_id": "CR_kwDOAPAIsc8AAAACHPEqNw", "head_sha": "0b971a1aef2fa27574d3c7c5f1a8a2eed6c2c1ec", "url": "https://api.github.com/repos/spack/spack/actions/jobs/9075501623", "html_url": "https://github.com/spack/spack/actions/runs/3314691390/jobs/5474724261", "status": "completed", "conclusion": "success", "started_at": "2022-10-24T17:44:11Z", "completed_at": "2022-10-24T17:45:11Z", "name": "prechecks / style", "steps": [{"name": "Set up job", "status": "completed", "conclusion": "success", "number": 1, "started_at": "2022-10-24T19:44:10.000+02:00", "completed_at": "2022-10-24T19:44:11.000+02:00"}, {"name": "Run actions/checkout@93ea575cb5d8a053eaa0ac8fa3b40d7e05a33cc8", "status": "completed", "conclusion": "success", "number": 2, "started_at": "2022-10-24T19:44:12.000+02:00", "completed_at": "2022-10-24T19:44:34.000+02:00"}, {"name": "Run actions/setup-python@13ae5bb136fac2878aff31522b9efb785519f984", "status": "completed", "conclusion": "success", "number": 3, "started_at": "2022-10-24T19:44:34.000+02:00", "completed_at": "2022-10-24T19:44:37.000+02:00"}, {"name": "Install Python packages", "status": "completed", "conclusion": "success", "number": 4, "started_at": "2022-10-24T19:44:38.000+02:00", "completed_at": "2022-10-24T19:44:43.000+02:00"}, {"name": "Setup git configuration", "status": "completed", "conclusion": "success", "number": 5, "started_at": "2022-10-24T19:44:43.000+02:00", "completed_at": "2022-10-24T19:44:43.000+02:00"}, {"name": "Run style tests", "status": "completed", "conclusion": "success", "number": 6, "started_at": "2022-10-24T19:44:43.000+02:00", "completed_at": "2022-10-24T19:45:10.000+02:00"}, {"name": "Post Run actions/setup-python@13ae5bb136fac2878aff31522b9efb785519f984", "status": "completed", "conclusion": "success", "number": 11, "started_at": "2022-10-24T19:45:10.000+02:00", "completed_at": "2022-10-24T19:45:11.000+02:00"}, {"name": "Post Run actions/checkout@93ea575cb5d8a053eaa0ac8fa3b40d7e05a33cc8", "status": "completed", "conclusion": "success", "number": 12, "started_at": "2022-10-24T19:45:11.000+02:00", "completed_at": "2022-10-24T19:45:11.000+02:00"}, {"name": "Complete job", "status": "completed", "conclusion": "success", "number": 13, "started_at": "2022-10-24T19:45:11.000+02:00", "completed_at": "2022-10-24T19:45:11.000+02:00"}], "check_run_url": "https://api.github.com/repos/spack/spack/check-runs/9075501623", "labels": ["ubuntu-latest"], "runner_id": 16, "runner_name": "GitHub Actions 16", "runner_group_id": 2, "runner_group_name": "GitHub Actions"}, {"id": 9075501767, "run_id": 3314691390, "run_url": "https://api.github.com/repos/spack/spack/actions/runs/3314691390", "run_attempt": 1, "node_id": "CR_kwDOAPAIsc8AAAACHPEqxw", "head_sha": "0b971a1aef2fa27574d3c7c5f1a8a2eed6c2c1ec", "url": "https://api.github.com/repos/spack/spack/actions/jobs/9075501767", "html_url": "https://github.com/spack/spack/actions/runs/3314691390/jobs/5474724369", "status": "completed", "conclusion": "success", "started_at": "2022-10-24T17:42:23Z", "completed_at": "2022-10-24T17:56:36Z", "name": "audit-ancient-python / package-audits", "steps": [{"name": "Set up job", "status": "completed", "conclusion": "success", "number": 1, "started_at": "2022-10-24T19:42:23.000+02:00", "completed_at": "2022-10-24T19:42:24.000+02:00"}, {"name": "Run actions/checkout@93ea575cb5d8a053eaa0ac8fa3b40d7e05a33cc8", "status": "completed", "conclusion": "success", "number": 2, "started_at": "2022-10-24T19:42:24.000+02:00", "completed_at": "2022-10-24T19:42:27.000+02:00"}, {"name": "Run actions/setup-python@13ae5bb136fac2878aff31522b9efb785519f984", "status": "completed", "conclusion": "success", "number": 3, "started_at": "2022-10-24T19:42:28.000+02:00", "completed_at": "2022-10-24T19:42:28.000+02:00"}, {"name": "Install Python packages", "status": "completed", "conclusion": "success", "number": 4, "started_at": "2022-10-24T19:42:28.000+02:00", "completed_at": "2022-10-24T19:42:42.000+02:00"}, {"name": "Package audits (with coverage)", "status": "completed", "conclusion": "success", "number": 5, "started_at": "2022-10-24T19:42:42.000+02:00", "completed_at": "2022-10-24T19:55:19.000+02:00"}, {"name": "Package audits (without coverage)", "status": "completed", "conclusion": "skipped", "number": 6, "started_at": "2022-10-24T19:55:20.000+02:00", "completed_at": "2022-10-24T19:55:20.000+02:00"}, {"name": "Run codecov/codecov-action@d9f34f8cd5cb3b3eb79b3e4b5dae3a16df499a70", "status": "completed", "conclusion": "success", "number": 7, "started_at": "2022-10-24T19:55:20.000+02:00", "completed_at": "2022-10-24T19:56:35.000+02:00"}, {"name": "Post Run actions/setup-python@13ae5bb136fac2878aff31522b9efb785519f984", "status": "completed", "conclusion": "success", "number": 13, "started_at": "2022-10-24T19:56:36.000+02:00", "completed_at": "2022-10-24T19:56:36.000+02:00"}, {"name": "Post Run actions/checkout@93ea575cb5d8a053eaa0ac8fa3b40d7e05a33cc8", "status": "completed", "conclusion": "success", "number": 14, "started_at": "2022-10-24T19:56:36.000+02:00", "completed_at": "2022-10-24T19:56:36.000+02:00"}, {"name": "Complete job", "status": "completed", "conclusion": "success", "number": 15, "started_at": "2022-10-24T19:56:36.000+02:00", "completed_at": "2022-10-24T19:56:36.000+02:00"}], "check_run_url": "https://api.github.com/repos/spack/spack/check-runs/9075501767", "labels": ["ubuntu-latest"], "runner_id": 11, "runner_name": "GitHub Actions 11", "runner_group_id": 2, "runner_group_name": "GitHub Actions"}, {"id": 9075501899, "run_id": 3314691390, "run_url": "https://api.github.com/repos/spack/spack/actions/runs/3314691390", "run_attempt": 1, "node_id": "CR_kwDOAPAIsc8AAAACHPErSw", "head_sha": "0b971a1aef2fa27574d3c7c5f1a8a2eed6c2c1ec", "url": "https://api.github.com/repos/spack/spack/actions/jobs/9075501899", "html_url": "https://github.com/spack/spack/actions/runs/3314691390/jobs/5474724465", "status": "completed", "conclusion": "success", "started_at": "2022-10-24T17:45:18Z", "completed_at": "2022-10-24T17:50:32Z", "name": "prechecks / audit / package-audits", "steps": [{"name": "Set up job", "status": "completed", "conclusion": "success", "number": 1, "started_at": "2022-10-24T19:45:18.000+02:00", "completed_at": "2022-10-24T19:45:20.000+02:00"}, {"name": "Run actions/checkout@93ea575cb5d8a053eaa0ac8fa3b40d7e05a33cc8", "status": "completed", "conclusion": "success", "number": 2, "started_at": "2022-10-24T19:45:20.000+02:00", "completed_at": "2022-10-24T19:45:24.000+02:00"}, {"name": "Run actions/setup-python@13ae5bb136fac2878aff31522b9efb785519f984", "status": "completed", "conclusion": "success", "number": 3, "started_at": "2022-10-24T19:45:24.000+02:00", "completed_at": "2022-10-24T19:45:24.000+02:00"}, {"name": "Install Python packages", "status": "completed", "conclusion": "success", "number": 4, "started_at": "2022-10-24T19:45:25.000+02:00", "completed_at": "2022-10-24T19:45:33.000+02:00"}, {"name": "Package audits (with coverage)", "status": "completed", "conclusion": "success", "number": 5, "started_at": "2022-10-24T19:45:34.000+02:00", "completed_at": "2022-10-24T19:49:11.000+02:00"}, {"name": "Package audits (without coverage)", "status": "completed", "conclusion": "skipped", "number": 6, "started_at": "2022-10-24T19:49:11.000+02:00", "completed_at": "2022-10-24T19:49:11.000+02:00"}, {"name": "Run codecov/codecov-action@d9f34f8cd5cb3b3eb79b3e4b5dae3a16df499a70", "status": "completed", "conclusion": "success", "number": 7, "started_at": "2022-10-24T19:49:11.000+02:00", "completed_at": "2022-10-24T19:50:29.000+02:00"}, {"name": "Post Run actions/setup-python@13ae5bb136fac2878aff31522b9efb785519f984", "status": "completed", "conclusion": "success", "number": 13, "started_at": "2022-10-24T19:50:29.000+02:00", "completed_at": "2022-10-24T19:50:29.000+02:00"}, {"name": "Post Run actions/checkout@93ea575cb5d8a053eaa0ac8fa3b40d7e05a33cc8", "status": "completed", "conclusion": "success", "number": 14, "started_at": "2022-10-24T19:50:32.000+02:00", "completed_at": "2022-10-24T19:50:29.000+02:00"}, {"name": "Complete job", "status": "completed", "conclusion": "success", "number": 15, "started_at": "2022-10-24T19:50:29.000+02:00", "completed_at": "2022-10-24T19:50:29.000+02:00"}], "check_run_url": "https://api.github.com/repos/spack/spack/check-runs/9075501899", "labels": ["ubuntu-latest"], "runner_id": 16, "runner_name": "GitHub Actions 16", "runner_group_id": 2, "runner_group_name": "GitHub Actions"}, {"id": 9075724109, "run_id": 3314691390, "run_url": "https://api.github.com/repos/spack/spack/actions/runs/3314691390", "run_attempt": 1, "node_id": "CR_kwDOAPAIsc8AAAACHPSPTQ", "head_sha": "0b971a1aef2fa27574d3c7c5f1a8a2eed6c2c1ec", "url": "https://api.github.com/repos/spack/spack/actions/jobs/9075724109", "html_url": "https://github.com/spack/spack/actions/runs/3314691390/jobs/5474886241", "status": "completed", "conclusion": "success", "started_at": "2022-10-24T17:50:38Z", "completed_at": "2022-10-24T17:50:40Z", "name": "all-prechecks", "steps": [{"name": "Set up job", "status": "completed", "conclusion": "success", "number": 1, "started_at": "2022-10-24T19:50:38.000+02:00", "completed_at": "2022-10-24T19:50:38.000+02:00"}, {"name": "Success", "status": "completed", "conclusion": "success", "number": 2, "started_at": "2022-10-24T19:50:38.000+02:00", "completed_at": "2022-10-24T19:50:38.000+02:00"}, {"name": "Complete job", "status": "completed", "conclusion": "success", "number": 3, "started_at": "2022-10-24T19:50:38.000+02:00", "completed_at": "2022-10-24T19:50:38.000+02:00"}], "check_run_url": "https://api.github.com/repos/spack/spack/check-runs/9075724109", "labels": ["ubuntu-latest"], "runner_id": 3, "runner_name": "GitHub Actions 3", "runner_group_id": 2, "runner_group_name": "GitHub Actions"}, {"id": 9075724583, "run_id": 3314691390, "run_url": "https://api.github.com/repos/spack/spack/actions/runs/3314691390", "run_attempt": 1, "node_id": "CR_kwDOAPAIsc8AAAACHPSRJw", "head_sha": "0b971a1aef2fa27574d3c7c5f1a8a2eed6c2c1ec", "url": "https://api.github.com/repos/spack/spack/actions/jobs/9075724583", "html_url": "https://github.com/spack/spack/actions/runs/3314691390/jobs/5474886563", "status": "completed", "conclusion": "success", "started_at": "2022-10-24T17:50:41Z", "completed_at": "2022-10-24T18:00:19Z", "name": "unit-tests / shell", "steps": [{"name": "Set up job", "status": "completed", "conclusion": "success", "number": 1, "started_at": "2022-10-24T19:50:40.000+02:00", "completed_at": "2022-10-24T19:50:42.000+02:00"}, {"name": "Run actions/checkout@93ea575cb5d8a053eaa0ac8fa3b40d7e05a33cc8", "status": "completed", "conclusion": "success", "number": 2, "started_at": "2022-10-24T19:50:42.000+02:00", "completed_at": "2022-10-24T19:51:10.000+02:00"}, {"name": "Run actions/setup-python@13ae5bb136fac2878aff31522b9efb785519f984", "status": "completed", "conclusion": "success", "number": 3, "started_at": "2022-10-24T19:51:10.000+02:00", "completed_at": "2022-10-24T19:51:10.000+02:00"}, {"name": "Install System packages", "status": "completed", "conclusion": "success", "number": 4, "started_at": "2022-10-24T19:51:10.000+02:00", "completed_at": "2022-10-24T19:51:29.000+02:00"}, {"name": "Install Python packages", "status": "completed", "conclusion": "success", "number": 5, "started_at": "2022-10-24T19:51:29.000+02:00", "completed_at": "2022-10-24T19:51:35.000+02:00"}, {"name": "Setup git configuration", "status": "completed", "conclusion": "success", "number": 6, "started_at": "2022-10-24T19:51:36.000+02:00", "completed_at": "2022-10-24T19:51:36.000+02:00"}, {"name": "Run shell tests", "status": "completed", "conclusion": "success", "number": 7, "started_at": "2022-10-24T19:51:36.000+02:00", "completed_at": "2022-10-24T20:00:13.000+02:00"}, {"name": "Run codecov/codecov-action@d9f34f8cd5cb3b3eb79b3e4b5dae3a16df499a70", "status": "completed", "conclusion": "success", "number": 8, "started_at": "2022-10-24T20:00:13.000+02:00", "completed_at": "2022-10-24T20:00:17.000+02:00"}, {"name": "Post Run actions/setup-python@13ae5bb136fac2878aff31522b9efb785519f984", "status": "completed", "conclusion": "success", "number": 15, "started_at": "2022-10-24T20:00:17.000+02:00", "completed_at": "2022-10-24T20:00:17.000+02:00"}, {"name": "Post Run actions/checkout@93ea575cb5d8a053eaa0ac8fa3b40d7e05a33cc8", "status": "completed", "conclusion": "success", "number": 16, "started_at": "2022-10-24T20:00:17.000+02:00", "completed_at": "2022-10-24T20:00:17.000+02:00"}, {"name": "Complete job", "status": "completed", "conclusion": "success", "number": 17, "started_at": "2022-10-24T20:00:17.000+02:00", "completed_at": "2022-10-24T20:00:17.000+02:00"}], "check_run_url": "https://api.github.com/repos/spack/spack/check-runs/9075724583", "labels": ["ubuntu-latest"], "runner_id": 6, "runner_name": "GitHub Actions 6", "runner_group_id": 2, "runner_group_name": "GitHub Actions"}, {"id": 9075724905, "run_id": 3314691390, "run_url": "https://api.github.com/repos/spack/spack/actions/runs/3314691390", "run_attempt": 1, "node_id": "CR_kwDOAPAIsc8AAAACHPSSaQ", "head_sha": "0b971a1aef2fa27574d3c7c5f1a8a2eed6c2c1ec", "url": "https://api.github.com/repos/spack/spack/actions/jobs/9075724905", "html_url": "https://github.com/spack/spack/actions/runs/3314691390/jobs/5474886789", "status": "completed", "conclusion": "success", "started_at": "2022-10-24T17:50:39Z", "completed_at": "2022-10-24T18:21:24Z", "name": "unit-tests / ubuntu (2.7, clingo, true)", "steps": [{"name": "Set up job", "status": "completed", "conclusion": "success", "number": 1, "started_at": "2022-10-24T19:50:38.000+02:00", "completed_at": "2022-10-24T19:50:40.000+02:00"}, {"name": "Run actions/checkout@93ea575cb5d8a053eaa0ac8fa3b40d7e05a33cc8", "status": "completed", "conclusion": "success", "number": 2, "started_at": "2022-10-24T19:50:40.000+02:00", "completed_at": "2022-10-24T19:51:01.000+02:00"}, {"name": "Run actions/setup-python@13ae5bb136fac2878aff31522b9efb785519f984", "status": "completed", "conclusion": "success", "number": 3, "started_at": "2022-10-24T19:51:01.000+02:00", "completed_at": "2022-10-24T19:51:01.000+02:00"}, {"name": "Install System packages", "status": "completed", "conclusion": "success", "number": 4, "started_at": "2022-10-24T19:51:01.000+02:00", "completed_at": "2022-10-24T19:51:18.000+02:00"}, {"name": "Install Python packages", "status": "completed", "conclusion": "success", "number": 5, "started_at": "2022-10-24T19:51:19.000+02:00", "completed_at": "2022-10-24T19:51:32.000+02:00"}, {"name": "Pin pathlib for Python 2.7", "status": "completed", "conclusion": "success", "number": 6, "started_at": "2022-10-24T19:51:32.000+02:00", "completed_at": "2022-10-24T19:51:33.000+02:00"}, {"name": "Setup git configuration", "status": "completed", "conclusion": "success", "number": 7, "started_at": "2022-10-24T19:51:33.000+02:00", "completed_at": "2022-10-24T19:51:33.000+02:00"}, {"name": "Bootstrap clingo", "status": "completed", "conclusion": "success", "number": 8, "started_at": "2022-10-24T19:51:33.000+02:00", "completed_at": "2022-10-24T19:52:23.000+02:00"}, {"name": "Run unit tests", "status": "completed", "conclusion": "success", "number": 9, "started_at": "2022-10-24T19:52:23.000+02:00", "completed_at": "2022-10-24T20:21:19.000+02:00"}, {"name": "Run codecov/codecov-action@d9f34f8cd5cb3b3eb79b3e4b5dae3a16df499a70", "status": "completed", "conclusion": "success", "number": 10, "started_at": "2022-10-24T20:21:19.000+02:00", "completed_at": "2022-10-24T20:21:22.000+02:00"}, {"name": "Post Run actions/setup-python@13ae5bb136fac2878aff31522b9efb785519f984", "status": "completed", "conclusion": "success", "number": 19, "started_at": "2022-10-24T20:21:24.000+02:00", "completed_at": "2022-10-24T20:21:24.000+02:00"}, {"name": "Post Run actions/checkout@93ea575cb5d8a053eaa0ac8fa3b40d7e05a33cc8", "status": "completed", "conclusion": "success", "number": 20, "started_at": "2022-10-24T20:21:24.000+02:00", "completed_at": "2022-10-24T20:21:24.000+02:00"}, {"name": "Complete job", "status": "completed", "conclusion": "success", "number": 21, "started_at": "2022-10-24T20:21:23.000+02:00", "completed_at": "2022-10-24T20:21:23.000+02:00"}], "check_run_url": "https://api.github.com/repos/spack/spack/check-runs/9075724905", "labels": ["ubuntu-latest"], "runner_id": 13, "runner_name": "GitHub Actions 13", "runner_group_id": 2, "runner_group_name": "GitHub Actions"}, {"id": 9075725046, "run_id": 3314691390, "run_url": "https://api.github.com/repos/spack/spack/actions/runs/3314691390", "run_attempt": 1, "node_id": "CR_kwDOAPAIsc8AAAACHPSS9g", "head_sha": "0b971a1aef2fa27574d3c7c5f1a8a2eed6c2c1ec", "url": "https://api.github.com/repos/spack/spack/actions/jobs/9075725046", "html_url": "https://github.com/spack/spack/actions/runs/3314691390/jobs/5474886894", "status": "completed", "conclusion": "success", "started_at": "2022-10-24T17:50:39Z", "completed_at": "2022-10-24T18:07:24Z", "name": "unit-tests / ubuntu (3.6, clingo, true)", "steps": [{"name": "Set up job", "status": "completed", "conclusion": "success", "number": 1, "started_at": "2022-10-24T19:50:39.000+02:00", "completed_at": "2022-10-24T19:50:40.000+02:00"}, {"name": "Run actions/checkout@93ea575cb5d8a053eaa0ac8fa3b40d7e05a33cc8", "status": "completed", "conclusion": "success", "number": 2, "started_at": "2022-10-24T19:50:40.000+02:00", "completed_at": "2022-10-24T19:51:03.000+02:00"}, {"name": "Run actions/setup-python@13ae5bb136fac2878aff31522b9efb785519f984", "status": "completed", "conclusion": "success", "number": 3, "started_at": "2022-10-24T19:51:04.000+02:00", "completed_at": "2022-10-24T19:51:04.000+02:00"}, {"name": "Install System packages", "status": "completed", "conclusion": "success", "number": 4, "started_at": "2022-10-24T19:51:04.000+02:00", "completed_at": "2022-10-24T19:51:21.000+02:00"}, {"name": "Install Python packages", "status": "completed", "conclusion": "success", "number": 5, "started_at": "2022-10-24T19:51:21.000+02:00", "completed_at": "2022-10-24T19:51:31.000+02:00"}, {"name": "Pin pathlib for Python 2.7", "status": "completed", "conclusion": "skipped", "number": 6, "started_at": "2022-10-24T19:51:32.000+02:00", "completed_at": "2022-10-24T19:51:32.000+02:00"}, {"name": "Setup git configuration", "status": "completed", "conclusion": "success", "number": 7, "started_at": "2022-10-24T19:51:32.000+02:00", "completed_at": "2022-10-24T19:51:32.000+02:00"}, {"name": "Bootstrap clingo", "status": "completed", "conclusion": "success", "number": 8, "started_at": "2022-10-24T19:51:32.000+02:00", "completed_at": "2022-10-24T19:52:21.000+02:00"}, {"name": "Run unit tests", "status": "completed", "conclusion": "success", "number": 9, "started_at": "2022-10-24T19:52:22.000+02:00", "completed_at": "2022-10-24T20:07:19.000+02:00"}, {"name": "Run codecov/codecov-action@d9f34f8cd5cb3b3eb79b3e4b5dae3a16df499a70", "status": "completed", "conclusion": "success", "number": 10, "started_at": "2022-10-24T20:07:19.000+02:00", "completed_at": "2022-10-24T20:07:23.000+02:00"}, {"name": "Post Run actions/setup-python@13ae5bb136fac2878aff31522b9efb785519f984", "status": "completed", "conclusion": "success", "number": 19, "started_at": "2022-10-24T20:07:23.000+02:00", "completed_at": "2022-10-24T20:07:23.000+02:00"}, {"name": "Post Run actions/checkout@93ea575cb5d8a053eaa0ac8fa3b40d7e05a33cc8", "status": "completed", "conclusion": "success", "number": 20, "started_at": "2022-10-24T20:07:23.000+02:00", "completed_at": "2022-10-24T20:07:23.000+02:00"}, {"name": "Complete job", "status": "completed", "conclusion": "success", "number": 21, "started_at": "2022-10-24T20:07:23.000+02:00", "completed_at": "2022-10-24T20:07:23.000+02:00"}], "check_run_url": "https://api.github.com/repos/spack/spack/check-runs/9075725046", "labels": ["ubuntu-latest"], "runner_id": 19, "runner_name": "GitHub Actions 19", "runner_group_id": 2, "runner_group_name": "GitHub Actions"}, {"id": 9075725191, "run_id": 3314691390, "run_url": "https://api.github.com/repos/spack/spack/actions/runs/3314691390", "run_attempt": 1, "node_id": "CR_kwDOAPAIsc8AAAACHPSThw", "head_sha": "0b971a1aef2fa27574d3c7c5f1a8a2eed6c2c1ec", "url": "https://api.github.com/repos/spack/spack/actions/jobs/9075725191", "html_url": "https://github.com/spack/spack/actions/runs/3314691390/jobs/5474887001", "status": "completed", "conclusion": "success", "started_at": "2022-10-24T17:50:42Z", "completed_at": "2022-10-24T18:12:11Z", "name": "unit-tests / ubuntu (3.7, clingo, true)", "steps": [{"name": "Set up job", "status": "completed", "conclusion": "success", "number": 1, "started_at": "2022-10-24T19:50:42.000+02:00", "completed_at": "2022-10-24T19:50:44.000+02:00"}, {"name": "Run actions/checkout@93ea575cb5d8a053eaa0ac8fa3b40d7e05a33cc8", "status": "completed", "conclusion": "success", "number": 2, "started_at": "2022-10-24T19:50:45.000+02:00", "completed_at": "2022-10-24T19:51:12.000+02:00"}, {"name": "Run actions/setup-python@13ae5bb136fac2878aff31522b9efb785519f984", "status": "completed", "conclusion": "success", "number": 3, "started_at": "2022-10-24T19:51:13.000+02:00", "completed_at": "2022-10-24T19:51:13.000+02:00"}, {"name": "Install System packages", "status": "completed", "conclusion": "success", "number": 4, "started_at": "2022-10-24T19:51:13.000+02:00", "completed_at": "2022-10-24T19:51:35.000+02:00"}, {"name": "Install Python packages", "status": "completed", "conclusion": "success", "number": 5, "started_at": "2022-10-24T19:51:35.000+02:00", "completed_at": "2022-10-24T19:51:49.000+02:00"}, {"name": "Pin pathlib for Python 2.7", "status": "completed", "conclusion": "skipped", "number": 6, "started_at": "2022-10-24T19:51:49.000+02:00", "completed_at": "2022-10-24T19:51:49.000+02:00"}, {"name": "Setup git configuration", "status": "completed", "conclusion": "success", "number": 7, "started_at": "2022-10-24T19:51:49.000+02:00", "completed_at": "2022-10-24T19:51:49.000+02:00"}, {"name": "Bootstrap clingo", "status": "completed", "conclusion": "success", "number": 8, "started_at": "2022-10-24T19:51:49.000+02:00", "completed_at": "2022-10-24T19:52:59.000+02:00"}, {"name": "Run unit tests", "status": "completed", "conclusion": "success", "number": 9, "started_at": "2022-10-24T19:53:00.000+02:00", "completed_at": "2022-10-24T20:12:05.000+02:00"}, {"name": "Run codecov/codecov-action@d9f34f8cd5cb3b3eb79b3e4b5dae3a16df499a70", "status": "completed", "conclusion": "success", "number": 10, "started_at": "2022-10-24T20:12:06.000+02:00", "completed_at": "2022-10-24T20:12:09.000+02:00"}, {"name": "Post Run actions/setup-python@13ae5bb136fac2878aff31522b9efb785519f984", "status": "completed", "conclusion": "success", "number": 19, "started_at": "2022-10-24T20:12:09.000+02:00", "completed_at": "2022-10-24T20:12:09.000+02:00"}, {"name": "Post Run actions/checkout@93ea575cb5d8a053eaa0ac8fa3b40d7e05a33cc8", "status": "completed", "conclusion": "success", "number": 20, "started_at": "2022-10-24T20:12:09.000+02:00", "completed_at": "2022-10-24T20:12:09.000+02:00"}, {"name": "Complete job", "status": "completed", "conclusion": "success", "number": 21, "started_at": "2022-10-24T20:12:09.000+02:00", "completed_at": "2022-10-24T20:12:09.000+02:00"}], "check_run_url": "https://api.github.com/repos/spack/spack/check-runs/9075725191", "labels": ["ubuntu-latest"], "runner_id": 20, "runner_name": "GitHub Actions 20", "runner_group_id": 2, "runner_group_name": "GitHub Actions"}, {"id": 9075725322, "run_id": 3314691390, "run_url": "https://api.github.com/repos/spack/spack/actions/runs/3314691390", "run_attempt": 1, "node_id": "CR_kwDOAPAIsc8AAAACHPSUCg", "head_sha": "0b971a1aef2fa27574d3c7c5f1a8a2eed6c2c1ec", "url": "https://api.github.com/repos/spack/spack/actions/jobs/9075725322", "html_url": "https://github.com/spack/spack/actions/runs/3314691390/jobs/5474887103", "status": "completed", "conclusion": "success", "started_at": "2022-10-24T17:50:48Z", "completed_at": "2022-10-24T18:07:10Z", "name": "unit-tests / ubuntu (3.8, clingo, true)", "steps": [{"name": "Set up job", "status": "completed", "conclusion": "success", "number": 1, "started_at": "2022-10-24T19:50:47.000+02:00", "completed_at": "2022-10-24T19:50:50.000+02:00"}, {"name": "Run actions/checkout@93ea575cb5d8a053eaa0ac8fa3b40d7e05a33cc8", "status": "completed", "conclusion": "success", "number": 2, "started_at": "2022-10-24T19:50:50.000+02:00", "completed_at": "2022-10-24T19:51:33.000+02:00"}, {"name": "Run actions/setup-python@13ae5bb136fac2878aff31522b9efb785519f984", "status": "completed", "conclusion": "success", "number": 3, "started_at": "2022-10-24T19:51:34.000+02:00", "completed_at": "2022-10-24T19:51:34.000+02:00"}, {"name": "Install System packages", "status": "completed", "conclusion": "success", "number": 4, "started_at": "2022-10-24T19:51:34.000+02:00", "completed_at": "2022-10-24T19:51:57.000+02:00"}, {"name": "Install Python packages", "status": "completed", "conclusion": "success", "number": 5, "started_at": "2022-10-24T19:51:57.000+02:00", "completed_at": "2022-10-24T19:52:09.000+02:00"}, {"name": "Pin pathlib for Python 2.7", "status": "completed", "conclusion": "skipped", "number": 6, "started_at": "2022-10-24T19:52:09.000+02:00", "completed_at": "2022-10-24T19:52:09.000+02:00"}, {"name": "Setup git configuration", "status": "completed", "conclusion": "success", "number": 7, "started_at": "2022-10-24T19:52:09.000+02:00", "completed_at": "2022-10-24T19:52:09.000+02:00"}, {"name": "Bootstrap clingo", "status": "completed", "conclusion": "success", "number": 8, "started_at": "2022-10-24T19:52:09.000+02:00", "completed_at": "2022-10-24T19:53:04.000+02:00"}, {"name": "Run unit tests", "status": "completed", "conclusion": "success", "number": 9, "started_at": "2022-10-24T19:53:04.000+02:00", "completed_at": "2022-10-24T20:07:04.000+02:00"}, {"name": "Run codecov/codecov-action@d9f34f8cd5cb3b3eb79b3e4b5dae3a16df499a70", "status": "completed", "conclusion": "success", "number": 10, "started_at": "2022-10-24T20:07:05.000+02:00", "completed_at": "2022-10-24T20:07:08.000+02:00"}, {"name": "Post Run actions/setup-python@13ae5bb136fac2878aff31522b9efb785519f984", "status": "completed", "conclusion": "success", "number": 19, "started_at": "2022-10-24T20:07:08.000+02:00", "completed_at": "2022-10-24T20:07:08.000+02:00"}, {"name": "Post Run actions/checkout@93ea575cb5d8a053eaa0ac8fa3b40d7e05a33cc8", "status": "completed", "conclusion": "success", "number": 20, "started_at": "2022-10-24T20:07:10.000+02:00", "completed_at": "2022-10-24T20:07:10.000+02:00"}, {"name": "Complete job", "status": "completed", "conclusion": "success", "number": 21, "started_at": "2022-10-24T20:07:08.000+02:00", "completed_at": "2022-10-24T20:07:08.000+02:00"}], "check_run_url": "https://api.github.com/repos/spack/spack/check-runs/9075725322", "labels": ["ubuntu-latest"], "runner_id": 3, "runner_name": "GitHub Actions 3", "runner_group_id": 2, "runner_group_name": "GitHub Actions"}, {"id": 9075725487, "run_id": 3314691390, "run_url": "https://api.github.com/repos/spack/spack/actions/runs/3314691390", "run_attempt": 1, "node_id": "CR_kwDOAPAIsc8AAAACHPSUrw", "head_sha": "0b971a1aef2fa27574d3c7c5f1a8a2eed6c2c1ec", "url": "https://api.github.com/repos/spack/spack/actions/jobs/9075725487", "html_url": "https://github.com/spack/spack/actions/runs/3314691390/jobs/5474887235", "status": "completed", "conclusion": "success", "started_at": "2022-10-24T17:56:00Z", "completed_at": "2022-10-24T18:14:15Z", "name": "unit-tests / ubuntu (3.9, clingo, true)", "steps": [{"name": "Set up job", "status": "completed", "conclusion": "success", "number": 1, "started_at": "2022-10-24T19:56:00.000+02:00", "completed_at": "2022-10-24T19:56:02.000+02:00"}, {"name": "Run actions/checkout@93ea575cb5d8a053eaa0ac8fa3b40d7e05a33cc8", "status": "completed", "conclusion": "success", "number": 2, "started_at": "2022-10-24T19:56:03.000+02:00", "completed_at": "2022-10-24T19:56:30.000+02:00"}, {"name": "Run actions/setup-python@13ae5bb136fac2878aff31522b9efb785519f984", "status": "completed", "conclusion": "success", "number": 3, "started_at": "2022-10-24T19:56:31.000+02:00", "completed_at": "2022-10-24T19:56:31.000+02:00"}, {"name": "Install System packages", "status": "completed", "conclusion": "success", "number": 4, "started_at": "2022-10-24T19:56:31.000+02:00", "completed_at": "2022-10-24T19:57:04.000+02:00"}, {"name": "Install Python packages", "status": "completed", "conclusion": "success", "number": 5, "started_at": "2022-10-24T19:57:04.000+02:00", "completed_at": "2022-10-24T19:57:18.000+02:00"}, {"name": "Pin pathlib for Python 2.7", "status": "completed", "conclusion": "skipped", "number": 6, "started_at": "2022-10-24T19:57:18.000+02:00", "completed_at": "2022-10-24T19:57:18.000+02:00"}, {"name": "Setup git configuration", "status": "completed", "conclusion": "success", "number": 7, "started_at": "2022-10-24T19:57:18.000+02:00", "completed_at": "2022-10-24T19:57:18.000+02:00"}, {"name": "Bootstrap clingo", "status": "completed", "conclusion": "success", "number": 8, "started_at": "2022-10-24T19:57:18.000+02:00", "completed_at": "2022-10-24T19:58:26.000+02:00"}, {"name": "Run unit tests", "status": "completed", "conclusion": "success", "number": 9, "started_at": "2022-10-24T19:58:26.000+02:00", "completed_at": "2022-10-24T20:14:09.000+02:00"}, {"name": "Run codecov/codecov-action@d9f34f8cd5cb3b3eb79b3e4b5dae3a16df499a70", "status": "completed", "conclusion": "success", "number": 10, "started_at": "2022-10-24T20:14:09.000+02:00", "completed_at": "2022-10-24T20:14:13.000+02:00"}, {"name": "Post Run actions/setup-python@13ae5bb136fac2878aff31522b9efb785519f984", "status": "completed", "conclusion": "success", "number": 19, "started_at": "2022-10-24T20:14:13.000+02:00", "completed_at": "2022-10-24T20:14:13.000+02:00"}, {"name": "Post Run actions/checkout@93ea575cb5d8a053eaa0ac8fa3b40d7e05a33cc8", "status": "completed", "conclusion": "success", "number": 20, "started_at": "2022-10-24T20:14:13.000+02:00", "completed_at": "2022-10-24T20:14:13.000+02:00"}, {"name": "Complete job", "status": "completed", "conclusion": "success", "number": 21, "started_at": "2022-10-24T20:14:13.000+02:00", "completed_at": "2022-10-24T20:14:13.000+02:00"}], "check_run_url": "https://api.github.com/repos/spack/spack/check-runs/9075725487", "labels": ["ubuntu-latest"], "runner_id": 7, "runner_name": "GitHub Actions 7", "runner_group_id": 2, "runner_group_name": "GitHub Actions"}, {"id": 9075725623, "run_id": 3314691390, "run_url": "https://api.github.com/repos/spack/spack/actions/runs/3314691390", "run_attempt": 1, "node_id": "CR_kwDOAPAIsc8AAAACHPSVNw", "head_sha": "0b971a1aef2fa27574d3c7c5f1a8a2eed6c2c1ec", "url": "https://api.github.com/repos/spack/spack/actions/jobs/9075725623", "html_url": "https://github.com/spack/spack/actions/runs/3314691390/jobs/5474887336", "status": "completed", "conclusion": "success", "started_at": "2022-10-24T17:50:39Z", "completed_at": "2022-10-24T18:37:45Z", "name": "unit-tests / ubuntu (3.10, clingo, true)", "steps": [{"name": "Set up job", "status": "completed", "conclusion": "success", "number": 1, "started_at": "2022-10-24T19:50:39.000+02:00", "completed_at": "2022-10-24T19:50:40.000+02:00"}, {"name": "Run actions/checkout@93ea575cb5d8a053eaa0ac8fa3b40d7e05a33cc8", "status": "completed", "conclusion": "success", "number": 2, "started_at": "2022-10-24T19:50:40.000+02:00", "completed_at": "2022-10-24T19:51:03.000+02:00"}, {"name": "Run actions/setup-python@13ae5bb136fac2878aff31522b9efb785519f984", "status": "completed", "conclusion": "success", "number": 3, "started_at": "2022-10-24T19:51:03.000+02:00", "completed_at": "2022-10-24T19:51:03.000+02:00"}, {"name": "Install System packages", "status": "completed", "conclusion": "success", "number": 4, "started_at": "2022-10-24T19:51:03.000+02:00", "completed_at": "2022-10-24T19:51:22.000+02:00"}, {"name": "Install Python packages", "status": "completed", "conclusion": "success", "number": 5, "started_at": "2022-10-24T19:51:22.000+02:00", "completed_at": "2022-10-24T19:51:31.000+02:00"}, {"name": "Pin pathlib for Python 2.7", "status": "completed", "conclusion": "skipped", "number": 6, "started_at": "2022-10-24T19:51:32.000+02:00", "completed_at": "2022-10-24T19:51:32.000+02:00"}, {"name": "Setup git configuration", "status": "completed", "conclusion": "success", "number": 7, "started_at": "2022-10-24T19:51:32.000+02:00", "completed_at": "2022-10-24T19:51:32.000+02:00"}, {"name": "Bootstrap clingo", "status": "completed", "conclusion": "success", "number": 8, "started_at": "2022-10-24T19:51:32.000+02:00", "completed_at": "2022-10-24T19:52:27.000+02:00"}, {"name": "Run unit tests", "status": "completed", "conclusion": "success", "number": 9, "started_at": "2022-10-24T19:52:28.000+02:00", "completed_at": "2022-10-24T20:37:39.000+02:00"}, {"name": "Run codecov/codecov-action@d9f34f8cd5cb3b3eb79b3e4b5dae3a16df499a70", "status": "completed", "conclusion": "success", "number": 10, "started_at": "2022-10-24T20:37:39.000+02:00", "completed_at": "2022-10-24T20:37:44.000+02:00"}, {"name": "Post Run actions/setup-python@13ae5bb136fac2878aff31522b9efb785519f984", "status": "completed", "conclusion": "success", "number": 19, "started_at": "2022-10-24T20:37:44.000+02:00", "completed_at": "2022-10-24T20:37:44.000+02:00"}, {"name": "Post Run actions/checkout@93ea575cb5d8a053eaa0ac8fa3b40d7e05a33cc8", "status": "completed", "conclusion": "success", "number": 20, "started_at": "2022-10-24T20:37:44.000+02:00", "completed_at": "2022-10-24T20:37:44.000+02:00"}, {"name": "Complete job", "status": "completed", "conclusion": "success", "number": 21, "started_at": "2022-10-24T20:37:44.000+02:00", "completed_at": "2022-10-24T20:37:44.000+02:00"}], "check_run_url": "https://api.github.com/repos/spack/spack/check-runs/9075725623", "labels": ["ubuntu-latest"], "runner_id": 15, "runner_name": "GitHub Actions 15", "runner_group_id": 2, "runner_group_name": "GitHub Actions"}, {"id": 9075725779, "run_id": 3314691390, "run_url": "https://api.github.com/repos/spack/spack/actions/runs/3314691390", "run_attempt": 1, "node_id": "CR_kwDOAPAIsc8AAAACHPSV0w", "head_sha": "0b971a1aef2fa27574d3c7c5f1a8a2eed6c2c1ec", "url": "https://api.github.com/repos/spack/spack/actions/jobs/9075725779", "html_url": "https://github.com/spack/spack/actions/runs/3314691390/jobs/5474887456", "status": "completed", "conclusion": "success", "started_at": "2022-10-24T17:50:39Z", "completed_at": "2022-10-24T18:11:24Z", "name": "unit-tests / ubuntu (2.7, original, true)", "steps": [{"name": "Set up job", "status": "completed", "conclusion": "success", "number": 1, "started_at": "2022-10-24T19:50:39.000+02:00", "completed_at": "2022-10-24T19:50:40.000+02:00"}, {"name": "Run actions/checkout@93ea575cb5d8a053eaa0ac8fa3b40d7e05a33cc8", "status": "completed", "conclusion": "success", "number": 2, "started_at": "2022-10-24T19:50:40.000+02:00", "completed_at": "2022-10-24T19:51:03.000+02:00"}, {"name": "Run actions/setup-python@13ae5bb136fac2878aff31522b9efb785519f984", "status": "completed", "conclusion": "success", "number": 3, "started_at": "2022-10-24T19:51:03.000+02:00", "completed_at": "2022-10-24T19:51:03.000+02:00"}, {"name": "Install System packages", "status": "completed", "conclusion": "success", "number": 4, "started_at": "2022-10-24T19:51:03.000+02:00", "completed_at": "2022-10-24T19:51:20.000+02:00"}, {"name": "Install Python packages", "status": "completed", "conclusion": "success", "number": 5, "started_at": "2022-10-24T19:51:21.000+02:00", "completed_at": "2022-10-24T19:51:36.000+02:00"}, {"name": "Pin pathlib for Python 2.7", "status": "completed", "conclusion": "success", "number": 6, "started_at": "2022-10-24T19:51:37.000+02:00", "completed_at": "2022-10-24T19:51:37.000+02:00"}, {"name": "Setup git configuration", "status": "completed", "conclusion": "success", "number": 7, "started_at": "2022-10-24T19:51:37.000+02:00", "completed_at": "2022-10-24T19:51:37.000+02:00"}, {"name": "Bootstrap clingo", "status": "completed", "conclusion": "skipped", "number": 8, "started_at": "2022-10-24T19:51:37.000+02:00", "completed_at": "2022-10-24T19:51:37.000+02:00"}, {"name": "Run unit tests", "status": "completed", "conclusion": "success", "number": 9, "started_at": "2022-10-24T19:51:37.000+02:00", "completed_at": "2022-10-24T20:11:19.000+02:00"}, {"name": "Run codecov/codecov-action@d9f34f8cd5cb3b3eb79b3e4b5dae3a16df499a70", "status": "completed", "conclusion": "success", "number": 10, "started_at": "2022-10-24T20:11:20.000+02:00", "completed_at": "2022-10-24T20:11:23.000+02:00"}, {"name": "Post Run actions/setup-python@13ae5bb136fac2878aff31522b9efb785519f984", "status": "completed", "conclusion": "success", "number": 19, "started_at": "2022-10-24T20:11:23.000+02:00", "completed_at": "2022-10-24T20:11:23.000+02:00"}, {"name": "Post Run actions/checkout@93ea575cb5d8a053eaa0ac8fa3b40d7e05a33cc8", "status": "completed", "conclusion": "success", "number": 20, "started_at": "2022-10-24T20:11:24.000+02:00", "completed_at": "2022-10-24T20:11:24.000+02:00"}, {"name": "Complete job", "status": "completed", "conclusion": "success", "number": 21, "started_at": "2022-10-24T20:11:23.000+02:00", "completed_at": "2022-10-24T20:11:23.000+02:00"}], "check_run_url": "https://api.github.com/repos/spack/spack/check-runs/9075725779", "labels": ["ubuntu-latest"], "runner_id": 16, "runner_name": "GitHub Actions 16", "runner_group_id": 2, "runner_group_name": "GitHub Actions"}, {"id": 9075725908, "run_id": 3314691390, "run_url": "https://api.github.com/repos/spack/spack/actions/runs/3314691390", "run_attempt": 1, "node_id": "CR_kwDOAPAIsc8AAAACHPSWVA", "head_sha": "0b971a1aef2fa27574d3c7c5f1a8a2eed6c2c1ec", "url": "https://api.github.com/repos/spack/spack/actions/jobs/9075725908", "html_url": "https://github.com/spack/spack/actions/runs/3314691390/jobs/5474887555", "status": "completed", "conclusion": "success", "started_at": "2022-10-24T17:50:40Z", "completed_at": "2022-10-24T18:21:39Z", "name": "unit-tests / ubuntu (3.10, original, true)", "steps": [{"name": "Set up job", "status": "completed", "conclusion": "success", "number": 1, "started_at": "2022-10-24T19:50:40.000+02:00", "completed_at": "2022-10-24T19:50:41.000+02:00"}, {"name": "Run actions/checkout@93ea575cb5d8a053eaa0ac8fa3b40d7e05a33cc8", "status": "completed", "conclusion": "success", "number": 2, "started_at": "2022-10-24T19:50:41.000+02:00", "completed_at": "2022-10-24T19:51:06.000+02:00"}, {"name": "Run actions/setup-python@13ae5bb136fac2878aff31522b9efb785519f984", "status": "completed", "conclusion": "success", "number": 3, "started_at": "2022-10-24T19:51:07.000+02:00", "completed_at": "2022-10-24T19:51:07.000+02:00"}, {"name": "Install System packages", "status": "completed", "conclusion": "success", "number": 4, "started_at": "2022-10-24T19:51:07.000+02:00", "completed_at": "2022-10-24T19:51:28.000+02:00"}, {"name": "Install Python packages", "status": "completed", "conclusion": "success", "number": 5, "started_at": "2022-10-24T19:51:28.000+02:00", "completed_at": "2022-10-24T19:51:39.000+02:00"}, {"name": "Pin pathlib for Python 2.7", "status": "completed", "conclusion": "skipped", "number": 6, "started_at": "2022-10-24T19:51:40.000+02:00", "completed_at": "2022-10-24T19:51:40.000+02:00"}, {"name": "Setup git configuration", "status": "completed", "conclusion": "success", "number": 7, "started_at": "2022-10-24T19:51:40.000+02:00", "completed_at": "2022-10-24T19:51:40.000+02:00"}, {"name": "Bootstrap clingo", "status": "completed", "conclusion": "skipped", "number": 8, "started_at": "2022-10-24T19:51:40.000+02:00", "completed_at": "2022-10-24T19:51:40.000+02:00"}, {"name": "Run unit tests", "status": "completed", "conclusion": "success", "number": 9, "started_at": "2022-10-24T19:51:40.000+02:00", "completed_at": "2022-10-24T20:21:34.000+02:00"}, {"name": "Run codecov/codecov-action@d9f34f8cd5cb3b3eb79b3e4b5dae3a16df499a70", "status": "completed", "conclusion": "success", "number": 10, "started_at": "2022-10-24T20:21:34.000+02:00", "completed_at": "2022-10-24T20:21:37.000+02:00"}, {"name": "Post Run actions/setup-python@13ae5bb136fac2878aff31522b9efb785519f984", "status": "completed", "conclusion": "success", "number": 19, "started_at": "2022-10-24T20:21:38.000+02:00", "completed_at": "2022-10-24T20:21:38.000+02:00"}, {"name": "Post Run actions/checkout@93ea575cb5d8a053eaa0ac8fa3b40d7e05a33cc8", "status": "completed", "conclusion": "success", "number": 20, "started_at": "2022-10-24T20:21:38.000+02:00", "completed_at": "2022-10-24T20:21:38.000+02:00"}, {"name": "Complete job", "status": "completed", "conclusion": "success", "number": 21, "started_at": "2022-10-24T20:21:38.000+02:00", "completed_at": "2022-10-24T20:21:38.000+02:00"}], "check_run_url": "https://api.github.com/repos/spack/spack/check-runs/9075725908", "labels": ["ubuntu-latest"], "runner_id": 17, "runner_name": "GitHub Actions 17", "runner_group_id": 2, "runner_group_name": "GitHub Actions"}, {"id": 9075726095, "run_id": 3314691390, "run_url": "https://api.github.com/repos/spack/spack/actions/runs/3314691390", "run_attempt": 1, "node_id": "CR_kwDOAPAIsc8AAAACHPSXDw", "head_sha": "0b971a1aef2fa27574d3c7c5f1a8a2eed6c2c1ec", "url": "https://api.github.com/repos/spack/spack/actions/jobs/9075726095", "html_url": "https://github.com/spack/spack/actions/runs/3314691390/jobs/5474887698", "status": "completed", "conclusion": "success", "started_at": "2022-10-24T17:50:40Z", "completed_at": "2022-10-24T18:08:58Z", "name": "unit-tests / clingo-cffi", "steps": [{"name": "Set up job", "status": "completed", "conclusion": "success", "number": 1, "started_at": "2022-10-24T19:50:40.000+02:00", "completed_at": "2022-10-24T19:50:42.000+02:00"}, {"name": "Run actions/checkout@93ea575cb5d8a053eaa0ac8fa3b40d7e05a33cc8", "status": "completed", "conclusion": "success", "number": 2, "started_at": "2022-10-24T19:50:42.000+02:00", "completed_at": "2022-10-24T19:51:20.000+02:00"}, {"name": "Run actions/setup-python@13ae5bb136fac2878aff31522b9efb785519f984", "status": "completed", "conclusion": "success", "number": 3, "started_at": "2022-10-24T19:51:20.000+02:00", "completed_at": "2022-10-24T19:51:20.000+02:00"}, {"name": "Install System packages", "status": "completed", "conclusion": "success", "number": 4, "started_at": "2022-10-24T19:51:20.000+02:00", "completed_at": "2022-10-24T19:51:41.000+02:00"}, {"name": "Install Python packages", "status": "completed", "conclusion": "success", "number": 5, "started_at": "2022-10-24T19:51:41.000+02:00", "completed_at": "2022-10-24T19:51:54.000+02:00"}, {"name": "Setup git configuration", "status": "completed", "conclusion": "success", "number": 6, "started_at": "2022-10-24T19:51:55.000+02:00", "completed_at": "2022-10-24T19:51:55.000+02:00"}, {"name": "Run unit tests (full suite with coverage)", "status": "completed", "conclusion": "success", "number": 7, "started_at": "2022-10-24T19:51:55.000+02:00", "completed_at": "2022-10-24T20:08:52.000+02:00"}, {"name": "Run codecov/codecov-action@d9f34f8cd5cb3b3eb79b3e4b5dae3a16df499a70", "status": "completed", "conclusion": "success", "number": 8, "started_at": "2022-10-24T20:08:52.000+02:00", "completed_at": "2022-10-24T20:08:55.000+02:00"}, {"name": "Post Run actions/setup-python@13ae5bb136fac2878aff31522b9efb785519f984", "status": "completed", "conclusion": "success", "number": 15, "started_at": "2022-10-24T20:08:56.000+02:00", "completed_at": "2022-10-24T20:08:56.000+02:00"}, {"name": "Post Run actions/checkout@93ea575cb5d8a053eaa0ac8fa3b40d7e05a33cc8", "status": "completed", "conclusion": "success", "number": 16, "started_at": "2022-10-24T20:08:56.000+02:00", "completed_at": "2022-10-24T20:08:56.000+02:00"}, {"name": "Complete job", "status": "completed", "conclusion": "success", "number": 17, "started_at": "2022-10-24T20:08:56.000+02:00", "completed_at": "2022-10-24T20:08:56.000+02:00"}], "check_run_url": "https://api.github.com/repos/spack/spack/check-runs/9075726095", "labels": ["ubuntu-latest"], "runner_id": 8, "runner_name": "GitHub Actions 8", "runner_group_id": 2, "runner_group_name": "GitHub Actions"}, {"id": 9075726278, "run_id": 3314691390, "run_url": "https://api.github.com/repos/spack/spack/actions/runs/3314691390", "run_attempt": 1, "node_id": "CR_kwDOAPAIsc8AAAACHPSXxg", "head_sha": "0b971a1aef2fa27574d3c7c5f1a8a2eed6c2c1ec", "url": "https://api.github.com/repos/spack/spack/actions/jobs/9075726278", "html_url": "https://github.com/spack/spack/actions/runs/3314691390/jobs/5474887823", "status": "completed", "conclusion": "success", "started_at": "2022-10-24T17:50:38Z", "completed_at": "2022-10-24T18:14:30Z", "name": "unit-tests / rhel8-platform-python", "steps": [{"name": "Set up job", "status": "completed", "conclusion": "success", "number": 1, "started_at": "2022-10-24T19:50:38.000+02:00", "completed_at": "2022-10-24T19:50:39.000+02:00"}, {"name": "Initialize containers", "status": "completed", "conclusion": "success", "number": 2, "started_at": "2022-10-24T19:50:39.000+02:00", "completed_at": "2022-10-24T19:50:46.000+02:00"}, {"name": "Install dependencies", "status": "completed", "conclusion": "success", "number": 3, "started_at": "2022-10-24T19:50:46.000+02:00", "completed_at": "2022-10-24T19:51:04.000+02:00"}, {"name": "Run actions/checkout@93ea575cb5d8a053eaa0ac8fa3b40d7e05a33cc8", "status": "completed", "conclusion": "success", "number": 4, "started_at": "2022-10-24T19:51:04.000+02:00", "completed_at": "2022-10-24T19:51:07.000+02:00"}, {"name": "Setup repo and non-root user", "status": "completed", "conclusion": "success", "number": 5, "started_at": "2022-10-24T19:51:07.000+02:00", "completed_at": "2022-10-24T19:51:41.000+02:00"}, {"name": "Run unit tests", "status": "completed", "conclusion": "success", "number": 6, "started_at": "2022-10-24T19:51:41.000+02:00", "completed_at": "2022-10-24T20:14:27.000+02:00"}, {"name": "Post Run actions/checkout@93ea575cb5d8a053eaa0ac8fa3b40d7e05a33cc8", "status": "completed", "conclusion": "success", "number": 11, "started_at": "2022-10-24T20:14:27.000+02:00", "completed_at": "2022-10-24T20:14:27.000+02:00"}, {"name": "Stop containers", "status": "completed", "conclusion": "success", "number": 12, "started_at": "2022-10-24T20:14:28.000+02:00", "completed_at": "2022-10-24T20:14:29.000+02:00"}, {"name": "Complete job", "status": "completed", "conclusion": "success", "number": 13, "started_at": "2022-10-24T20:14:29.000+02:00", "completed_at": "2022-10-24T20:14:29.000+02:00"}], "check_run_url": "https://api.github.com/repos/spack/spack/check-runs/9075726278", "labels": ["ubuntu-latest"], "runner_id": 10, "runner_name": "GitHub Actions 10", "runner_group_id": 2, "runner_group_name": "GitHub Actions"}, {"id": 9075726446, "run_id": 3314691390, "run_url": "https://api.github.com/repos/spack/spack/actions/runs/3314691390", "run_attempt": 1, "node_id": "CR_kwDOAPAIsc8AAAACHPSYbg", "head_sha": "0b971a1aef2fa27574d3c7c5f1a8a2eed6c2c1ec", "url": "https://api.github.com/repos/spack/spack/actions/jobs/9075726446", "html_url": "https://github.com/spack/spack/actions/runs/3314691390/jobs/5474887957", "status": "completed", "conclusion": "success", "started_at": "2022-10-24T17:56:44Z", "completed_at": "2022-10-24T17:59:49Z", "name": "bootstrap / fedora-clingo-sources", "steps": [{"name": "Set up job", "status": "completed", "conclusion": "success", "number": 1, "started_at": "2022-10-24T19:56:43.000+02:00", "completed_at": "2022-10-24T19:56:45.000+02:00"}, {"name": "Initialize containers", "status": "completed", "conclusion": "success", "number": 2, "started_at": "2022-10-24T19:56:45.000+02:00", "completed_at": "2022-10-24T19:56:52.000+02:00"}, {"name": "Install dependencies", "status": "completed", "conclusion": "success", "number": 3, "started_at": "2022-10-24T19:56:52.000+02:00", "completed_at": "2022-10-24T19:58:14.000+02:00"}, {"name": "Checkout", "status": "completed", "conclusion": "success", "number": 4, "started_at": "2022-10-24T19:58:15.000+02:00", "completed_at": "2022-10-24T19:58:52.000+02:00"}, {"name": "Setup non-root user", "status": "completed", "conclusion": "success", "number": 5, "started_at": "2022-10-24T19:58:52.000+02:00", "completed_at": "2022-10-24T19:58:52.000+02:00"}, {"name": "Setup repo", "status": "completed", "conclusion": "success", "number": 6, "started_at": "2022-10-24T19:58:53.000+02:00", "completed_at": "2022-10-24T19:58:53.000+02:00"}, {"name": "Bootstrap clingo", "status": "completed", "conclusion": "success", "number": 7, "started_at": "2022-10-24T19:58:53.000+02:00", "completed_at": "2022-10-24T19:59:46.000+02:00"}, {"name": "Post Checkout", "status": "completed", "conclusion": "success", "number": 13, "started_at": "2022-10-24T19:59:46.000+02:00", "completed_at": "2022-10-24T19:59:46.000+02:00"}, {"name": "Stop containers", "status": "completed", "conclusion": "success", "number": 14, "started_at": "2022-10-24T19:59:47.000+02:00", "completed_at": "2022-10-24T19:59:47.000+02:00"}, {"name": "Complete job", "status": "completed", "conclusion": "success", "number": 15, "started_at": "2022-10-24T19:59:47.000+02:00", "completed_at": "2022-10-24T19:59:47.000+02:00"}], "check_run_url": "https://api.github.com/repos/spack/spack/check-runs/9075726446", "labels": ["ubuntu-latest"], "runner_id": 11, "runner_name": "GitHub Actions 11", "runner_group_id": 2, "runner_group_name": "GitHub Actions"}, {"id": 9075726599, "run_id": 3314691390, "run_url": "https://api.github.com/repos/spack/spack/actions/runs/3314691390", "run_attempt": 1, "node_id": "CR_kwDOAPAIsc8AAAACHPSZBw", "head_sha": "0b971a1aef2fa27574d3c7c5f1a8a2eed6c2c1ec", "url": "https://api.github.com/repos/spack/spack/actions/jobs/9075726599", "html_url": "https://github.com/spack/spack/actions/runs/3314691390/jobs/5474888072", "status": "completed", "conclusion": "success", "started_at": "2022-10-24T17:59:00Z", "completed_at": "2022-10-24T18:45:31Z", "name": "unit-tests / macos (3.8)", "steps": [{"name": "Set up job", "status": "completed", "conclusion": "success", "number": 1, "started_at": "2022-10-24T19:59:00.000+02:00", "completed_at": "2022-10-24T19:59:03.000+02:00"}, {"name": "Run actions/checkout@93ea575cb5d8a053eaa0ac8fa3b40d7e05a33cc8", "status": "completed", "conclusion": "success", "number": 2, "started_at": "2022-10-24T19:59:03.000+02:00", "completed_at": "2022-10-24T19:59:36.000+02:00"}, {"name": "Run actions/setup-python@13ae5bb136fac2878aff31522b9efb785519f984", "status": "completed", "conclusion": "success", "number": 3, "started_at": "2022-10-24T19:59:37.000+02:00", "completed_at": "2022-10-24T19:59:37.000+02:00"}, {"name": "Install Python packages", "status": "completed", "conclusion": "success", "number": 4, "started_at": "2022-10-24T19:59:37.000+02:00", "completed_at": "2022-10-24T19:59:48.000+02:00"}, {"name": "Setup Homebrew packages", "status": "completed", "conclusion": "success", "number": 5, "started_at": "2022-10-24T19:59:49.000+02:00", "completed_at": "2022-10-24T20:00:32.000+02:00"}, {"name": "Run unit tests", "status": "completed", "conclusion": "success", "number": 6, "started_at": "2022-10-24T20:00:32.000+02:00", "completed_at": "2022-10-24T20:45:24.000+02:00"}, {"name": "Run codecov/codecov-action@d9f34f8cd5cb3b3eb79b3e4b5dae3a16df499a70", "status": "completed", "conclusion": "success", "number": 7, "started_at": "2022-10-24T20:45:25.000+02:00", "completed_at": "2022-10-24T20:45:29.000+02:00"}, {"name": "Post Run actions/setup-python@13ae5bb136fac2878aff31522b9efb785519f984", "status": "completed", "conclusion": "success", "number": 13, "started_at": "2022-10-24T20:45:29.000+02:00", "completed_at": "2022-10-24T20:45:29.000+02:00"}, {"name": "Post Run actions/checkout@93ea575cb5d8a053eaa0ac8fa3b40d7e05a33cc8", "status": "completed", "conclusion": "success", "number": 14, "started_at": "2022-10-24T20:45:30.000+02:00", "completed_at": "2022-10-24T20:45:30.000+02:00"}, {"name": "Complete job", "status": "completed", "conclusion": "success", "number": 15, "started_at": "2022-10-24T20:45:30.000+02:00", "completed_at": "2022-10-24T20:45:30.000+02:00"}], "check_run_url": "https://api.github.com/repos/spack/spack/check-runs/9075726599", "labels": ["macos-latest"], "runner_id": 9, "runner_name": "GitHub Actions 9", "runner_group_id": 2, "runner_group_name": "GitHub Actions"}, {"id": 9075726783, "run_id": 3314691390, "run_url": "https://api.github.com/repos/spack/spack/actions/runs/3314691390", "run_attempt": 1, "node_id": "CR_kwDOAPAIsc8AAAACHPSZvw", "head_sha": "0b971a1aef2fa27574d3c7c5f1a8a2eed6c2c1ec", "url": "https://api.github.com/repos/spack/spack/actions/jobs/9075726783", "html_url": "https://github.com/spack/spack/actions/runs/3314691390/jobs/5474888221", "status": "completed", "conclusion": "success", "started_at": "2022-10-24T17:57:27Z", "completed_at": "2022-10-24T18:01:27Z", "name": "bootstrap / macos-clingo-binaries (macos-11)", "steps": [{"name": "Set up job", "status": "completed", "conclusion": "success", "number": 1, "started_at": "2022-10-24T19:57:24.000+02:00", "completed_at": "2022-10-24T19:57:26.000+02:00"}, {"name": "Install dependencies", "status": "completed", "conclusion": "success", "number": 2, "started_at": "2022-10-24T19:57:29.000+02:00", "completed_at": "2022-10-24T19:57:38.000+02:00"}, {"name": "Checkout", "status": "completed", "conclusion": "success", "number": 3, "started_at": "2022-10-24T19:57:41.000+02:00", "completed_at": "2022-10-24T19:57:49.000+02:00"}, {"name": "Bootstrap clingo", "status": "completed", "conclusion": "success", "number": 4, "started_at": "2022-10-24T19:57:51.000+02:00", "completed_at": "2022-10-24T20:01:23.000+02:00"}, {"name": "Post Checkout", "status": "completed", "conclusion": "success", "number": 8, "started_at": "2022-10-24T20:01:25.000+02:00", "completed_at": "2022-10-24T20:01:23.000+02:00"}, {"name": "Complete job", "status": "completed", "conclusion": "success", "number": 9, "started_at": "2022-10-24T20:01:23.000+02:00", "completed_at": "2022-10-24T20:01:23.000+02:00"}], "check_run_url": "https://api.github.com/repos/spack/spack/check-runs/9075726783", "labels": ["macos-11"], "runner_id": 1, "runner_name": "Hosted Agent", "runner_group_id": 2, "runner_group_name": "GitHub Actions"}, {"id": 9075727072, "run_id": 3314691390, "run_url": "https://api.github.com/repos/spack/spack/actions/runs/3314691390", "run_attempt": 1, "node_id": "CR_kwDOAPAIsc8AAAACHPSa4A", "head_sha": "0b971a1aef2fa27574d3c7c5f1a8a2eed6c2c1ec", "url": "https://api.github.com/repos/spack/spack/actions/jobs/9075727072", "html_url": "https://github.com/spack/spack/actions/runs/3314691390/jobs/5474888446", "status": "completed", "conclusion": "success", "started_at": "2022-10-24T17:58:18Z", "completed_at": "2022-10-24T18:02:33Z", "name": "bootstrap / macos-clingo-binaries (macos-12)", "steps": [{"name": "Set up job", "status": "completed", "conclusion": "success", "number": 1, "started_at": "2022-10-24T19:58:18.000+02:00", "completed_at": "2022-10-24T19:58:20.000+02:00"}, {"name": "Install dependencies", "status": "completed", "conclusion": "success", "number": 2, "started_at": "2022-10-24T19:58:21.000+02:00", "completed_at": "2022-10-24T19:58:37.000+02:00"}, {"name": "Checkout", "status": "completed", "conclusion": "success", "number": 3, "started_at": "2022-10-24T19:58:37.000+02:00", "completed_at": "2022-10-24T19:58:46.000+02:00"}, {"name": "Bootstrap clingo", "status": "completed", "conclusion": "success", "number": 4, "started_at": "2022-10-24T19:58:46.000+02:00", "completed_at": "2022-10-24T20:02:31.000+02:00"}, {"name": "Post Checkout", "status": "completed", "conclusion": "success", "number": 8, "started_at": "2022-10-24T20:02:32.000+02:00", "completed_at": "2022-10-24T20:02:32.000+02:00"}, {"name": "Complete job", "status": "completed", "conclusion": "success", "number": 9, "started_at": "2022-10-24T20:02:32.000+02:00", "completed_at": "2022-10-24T20:02:32.000+02:00"}], "check_run_url": "https://api.github.com/repos/spack/spack/check-runs/9075727072", "labels": ["macos-12"], "runner_id": 18, "runner_name": "GitHub Actions 18", "runner_group_id": 2, "runner_group_name": "GitHub Actions"}, {"id": 9075727237, "run_id": 3314691390, "run_url": "https://api.github.com/repos/spack/spack/actions/runs/3314691390", "run_attempt": 1, "node_id": "CR_kwDOAPAIsc8AAAACHPSbhQ", "head_sha": "0b971a1aef2fa27574d3c7c5f1a8a2eed6c2c1ec", "url": "https://api.github.com/repos/spack/spack/actions/jobs/9075727237", "html_url": "https://github.com/spack/spack/actions/runs/3314691390/jobs/5474888577", "status": "completed", "conclusion": "success", "started_at": "2022-10-24T18:00:07Z", "completed_at": "2022-10-24T18:02:37Z", "name": "bootstrap / opensuse-clingo-sources", "steps": [{"name": "Set up job", "status": "completed", "conclusion": "success", "number": 1, "started_at": "2022-10-24T20:00:06.000+02:00", "completed_at": "2022-10-24T20:00:07.000+02:00"}, {"name": "Initialize containers", "status": "completed", "conclusion": "success", "number": 2, "started_at": "2022-10-24T20:00:07.000+02:00", "completed_at": "2022-10-24T20:00:11.000+02:00"}, {"name": "Install dependencies", "status": "completed", "conclusion": "success", "number": 3, "started_at": "2022-10-24T20:00:12.000+02:00", "completed_at": "2022-10-24T20:01:28.000+02:00"}, {"name": "Checkout", "status": "completed", "conclusion": "success", "number": 4, "started_at": "2022-10-24T20:01:28.000+02:00", "completed_at": "2022-10-24T20:01:49.000+02:00"}, {"name": "Setup repo", "status": "completed", "conclusion": "success", "number": 5, "started_at": "2022-10-24T20:01:49.000+02:00", "completed_at": "2022-10-24T20:01:49.000+02:00"}, {"name": "Bootstrap clingo", "status": "completed", "conclusion": "success", "number": 6, "started_at": "2022-10-24T20:01:49.000+02:00", "completed_at": "2022-10-24T20:02:34.000+02:00"}, {"name": "Post Checkout", "status": "completed", "conclusion": "success", "number": 11, "started_at": "2022-10-24T20:02:34.000+02:00", "completed_at": "2022-10-24T20:02:35.000+02:00"}, {"name": "Stop containers", "status": "completed", "conclusion": "success", "number": 12, "started_at": "2022-10-24T20:02:35.000+02:00", "completed_at": "2022-10-24T20:02:36.000+02:00"}, {"name": "Complete job", "status": "completed", "conclusion": "success", "number": 13, "started_at": "2022-10-24T20:02:36.000+02:00", "completed_at": "2022-10-24T20:02:36.000+02:00"}], "check_run_url": "https://api.github.com/repos/spack/spack/check-runs/9075727237", "labels": ["ubuntu-latest"], "runner_id": 4, "runner_name": "GitHub Actions 4", "runner_group_id": 2, "runner_group_name": "GitHub Actions"}, {"id": 9075727428, "run_id": 3314691390, "run_url": "https://api.github.com/repos/spack/spack/actions/runs/3314691390", "run_attempt": 1, "node_id": "CR_kwDOAPAIsc8AAAACHPScRA", "head_sha": "0b971a1aef2fa27574d3c7c5f1a8a2eed6c2c1ec", "url": "https://api.github.com/repos/spack/spack/actions/jobs/9075727428", "html_url": "https://github.com/spack/spack/actions/runs/3314691390/jobs/5474888715", "status": "completed", "conclusion": "success", "started_at": "2022-10-24T17:59:56Z", "completed_at": "2022-10-24T18:04:56Z", "name": "bootstrap / ubuntu-clingo-binaries", "steps": [{"name": "Set up job", "status": "completed", "conclusion": "success", "number": 1, "started_at": "2022-10-24T19:59:55.000+02:00", "completed_at": "2022-10-24T19:59:56.000+02:00"}, {"name": "Checkout", "status": "completed", "conclusion": "success", "number": 2, "started_at": "2022-10-24T19:59:56.000+02:00", "completed_at": "2022-10-24T20:00:18.000+02:00"}, {"name": "Setup repo", "status": "completed", "conclusion": "success", "number": 3, "started_at": "2022-10-24T20:00:18.000+02:00", "completed_at": "2022-10-24T20:00:18.000+02:00"}, {"name": "Bootstrap clingo", "status": "completed", "conclusion": "success", "number": 4, "started_at": "2022-10-24T20:00:18.000+02:00", "completed_at": "2022-10-24T20:04:55.000+02:00"}, {"name": "Post Checkout", "status": "completed", "conclusion": "success", "number": 8, "started_at": "2022-10-24T20:04:55.000+02:00", "completed_at": "2022-10-24T20:04:55.000+02:00"}, {"name": "Complete job", "status": "completed", "conclusion": "success", "number": 9, "started_at": "2022-10-24T20:04:55.000+02:00", "completed_at": "2022-10-24T20:04:55.000+02:00"}], "check_run_url": "https://api.github.com/repos/spack/spack/check-runs/9075727428", "labels": ["ubuntu-20.04"], "runner_id": 11, "runner_name": "GitHub Actions 11", "runner_group_id": 2, "runner_group_name": "GitHub Actions"}, {"id": 9075727570, "run_id": 3314691390, "run_url": "https://api.github.com/repos/spack/spack/actions/runs/3314691390", "run_attempt": 1, "node_id": "CR_kwDOAPAIsc8AAAACHPSc0g", "head_sha": "0b971a1aef2fa27574d3c7c5f1a8a2eed6c2c1ec", "url": "https://api.github.com/repos/spack/spack/actions/jobs/9075727570", "html_url": "https://github.com/spack/spack/actions/runs/3314691390/jobs/5474888831", "status": "completed", "conclusion": "success", "started_at": "2022-10-24T18:01:35Z", "completed_at": "2022-10-24T18:03:52Z", "name": "bootstrap / ubuntu-clingo-binaries-and-patchelf", "steps": [{"name": "Set up job", "status": "completed", "conclusion": "success", "number": 1, "started_at": "2022-10-24T20:01:35.000+02:00", "completed_at": "2022-10-24T20:01:36.000+02:00"}, {"name": "Initialize containers", "status": "completed", "conclusion": "success", "number": 2, "started_at": "2022-10-24T20:01:36.000+02:00", "completed_at": "2022-10-24T20:01:41.000+02:00"}, {"name": "Install dependencies", "status": "completed", "conclusion": "success", "number": 3, "started_at": "2022-10-24T20:01:42.000+02:00", "completed_at": "2022-10-24T20:02:12.000+02:00"}, {"name": "Checkout", "status": "completed", "conclusion": "success", "number": 4, "started_at": "2022-10-24T20:02:12.000+02:00", "completed_at": "2022-10-24T20:03:03.000+02:00"}, {"name": "Setup non-root user", "status": "completed", "conclusion": "success", "number": 5, "started_at": "2022-10-24T20:03:03.000+02:00", "completed_at": "2022-10-24T20:03:03.000+02:00"}, {"name": "Setup repo", "status": "completed", "conclusion": "success", "number": 6, "started_at": "2022-10-24T20:03:03.000+02:00", "completed_at": "2022-10-24T20:03:03.000+02:00"}, {"name": "Bootstrap clingo", "status": "completed", "conclusion": "success", "number": 7, "started_at": "2022-10-24T20:03:05.000+02:00", "completed_at": "2022-10-24T20:03:49.000+02:00"}, {"name": "Post Checkout", "status": "completed", "conclusion": "success", "number": 13, "started_at": "2022-10-24T20:03:49.000+02:00", "completed_at": "2022-10-24T20:03:50.000+02:00"}, {"name": "Stop containers", "status": "completed", "conclusion": "success", "number": 14, "started_at": "2022-10-24T20:03:50.000+02:00", "completed_at": "2022-10-24T20:03:51.000+02:00"}, {"name": "Complete job", "status": "completed", "conclusion": "success", "number": 15, "started_at": "2022-10-24T20:03:51.000+02:00", "completed_at": "2022-10-24T20:03:51.000+02:00"}], "check_run_url": "https://api.github.com/repos/spack/spack/check-runs/9075727570", "labels": ["ubuntu-latest"], "runner_id": 1, "runner_name": "Hosted Agent", "runner_group_id": 2, "runner_group_name": "GitHub Actions"}, {"id": 9075727762, "run_id": 3314691390, "run_url": "https://api.github.com/repos/spack/spack/actions/runs/3314691390", "run_attempt": 1, "node_id": "CR_kwDOAPAIsc8AAAACHPSdkg", "head_sha": "0b971a1aef2fa27574d3c7c5f1a8a2eed6c2c1ec", "url": "https://api.github.com/repos/spack/spack/actions/jobs/9075727762", "html_url": "https://github.com/spack/spack/actions/runs/3314691390/jobs/5474888980", "status": "completed", "conclusion": "success", "started_at": "2022-10-24T18:02:43Z", "completed_at": "2022-10-24T18:04:30Z", "name": "bootstrap / ubuntu-clingo-sources", "steps": [{"name": "Set up job", "status": "completed", "conclusion": "success", "number": 1, "started_at": "2022-10-24T20:02:43.000+02:00", "completed_at": "2022-10-24T20:02:44.000+02:00"}, {"name": "Initialize containers", "status": "completed", "conclusion": "success", "number": 2, "started_at": "2022-10-24T20:02:44.000+02:00", "completed_at": "2022-10-24T20:02:49.000+02:00"}, {"name": "Install dependencies", "status": "completed", "conclusion": "success", "number": 3, "started_at": "2022-10-24T20:02:49.000+02:00", "completed_at": "2022-10-24T20:03:15.000+02:00"}, {"name": "Checkout", "status": "completed", "conclusion": "success", "number": 4, "started_at": "2022-10-24T20:03:16.000+02:00", "completed_at": "2022-10-24T20:03:43.000+02:00"}, {"name": "Setup non-root user", "status": "completed", "conclusion": "success", "number": 5, "started_at": "2022-10-24T20:03:43.000+02:00", "completed_at": "2022-10-24T20:03:44.000+02:00"}, {"name": "Setup repo", "status": "completed", "conclusion": "success", "number": 6, "started_at": "2022-10-24T20:03:44.000+02:00", "completed_at": "2022-10-24T20:03:44.000+02:00"}, {"name": "Bootstrap clingo", "status": "completed", "conclusion": "success", "number": 7, "started_at": "2022-10-24T20:03:44.000+02:00", "completed_at": "2022-10-24T20:04:27.000+02:00"}, {"name": "Post Checkout", "status": "completed", "conclusion": "success", "number": 13, "started_at": "2022-10-24T20:04:27.000+02:00", "completed_at": "2022-10-24T20:04:28.000+02:00"}, {"name": "Stop containers", "status": "completed", "conclusion": "success", "number": 14, "started_at": "2022-10-24T20:04:28.000+02:00", "completed_at": "2022-10-24T20:04:29.000+02:00"}, {"name": "Complete job", "status": "completed", "conclusion": "success", "number": 15, "started_at": "2022-10-24T20:04:29.000+02:00", "completed_at": "2022-10-24T20:04:29.000+02:00"}], "check_run_url": "https://api.github.com/repos/spack/spack/check-runs/9075727762", "labels": ["ubuntu-latest"], "runner_id": 4, "runner_name": "GitHub Actions 4", "runner_group_id": 2, "runner_group_name": "GitHub Actions"}, {"id": 9075727929, "run_id": 3314691390, "run_url": "https://api.github.com/repos/spack/spack/actions/runs/3314691390", "run_attempt": 1, "node_id": "CR_kwDOAPAIsc8AAAACHPSeOQ", "head_sha": "0b971a1aef2fa27574d3c7c5f1a8a2eed6c2c1ec", "url": "https://api.github.com/repos/spack/spack/actions/jobs/9075727929", "html_url": "https://github.com/spack/spack/actions/runs/3314691390/jobs/5474889117", "status": "completed", "conclusion": "success", "started_at": "2022-10-24T18:00:29Z", "completed_at": "2022-10-24T18:01:59Z", "name": "bootstrap / macos-clingo-sources", "steps": [{"name": "Set up job", "status": "completed", "conclusion": "success", "number": 1, "started_at": "2022-10-24T20:00:28.000+02:00", "completed_at": "2022-10-24T20:00:30.000+02:00"}, {"name": "Install dependencies", "status": "completed", "conclusion": "success", "number": 2, "started_at": "2022-10-24T20:00:30.000+02:00", "completed_at": "2022-10-24T20:00:46.000+02:00"}, {"name": "Checkout", "status": "completed", "conclusion": "success", "number": 3, "started_at": "2022-10-24T20:00:46.000+02:00", "completed_at": "2022-10-24T20:00:55.000+02:00"}, {"name": "Bootstrap clingo", "status": "completed", "conclusion": "success", "number": 4, "started_at": "2022-10-24T20:00:55.000+02:00", "completed_at": "2022-10-24T20:01:57.000+02:00"}, {"name": "Post Checkout", "status": "completed", "conclusion": "success", "number": 8, "started_at": "2022-10-24T20:01:57.000+02:00", "completed_at": "2022-10-24T20:01:57.000+02:00"}, {"name": "Complete job", "status": "completed", "conclusion": "success", "number": 9, "started_at": "2022-10-24T20:01:57.000+02:00", "completed_at": "2022-10-24T20:01:58.000+02:00"}], "check_run_url": "https://api.github.com/repos/spack/spack/check-runs/9075727929", "labels": ["macos-latest"], "runner_id": 6, "runner_name": "GitHub Actions 6", "runner_group_id": 2, "runner_group_name": "GitHub Actions"}, {"id": 9075728083, "run_id": 3314691390, "run_url": "https://api.github.com/repos/spack/spack/actions/runs/3314691390", "run_attempt": 1, "node_id": "CR_kwDOAPAIsc8AAAACHPSe0w", "head_sha": "0b971a1aef2fa27574d3c7c5f1a8a2eed6c2c1ec", "url": "https://api.github.com/repos/spack/spack/actions/jobs/9075728083", "html_url": "https://github.com/spack/spack/actions/runs/3314691390/jobs/5474889239", "status": "completed", "conclusion": "success", "started_at": "2022-10-24T18:02:09Z", "completed_at": "2022-10-24T18:07:02Z", "name": "bootstrap / macos-gnupg-binaries", "steps": [{"name": "Set up job", "status": "completed", "conclusion": "success", "number": 1, "started_at": "2022-10-24T20:02:09.000+02:00", "completed_at": "2022-10-24T20:02:14.000+02:00"}, {"name": "Install dependencies", "status": "completed", "conclusion": "success", "number": 2, "started_at": "2022-10-24T20:02:14.000+02:00", "completed_at": "2022-10-24T20:02:25.000+02:00"}, {"name": "Checkout", "status": "completed", "conclusion": "success", "number": 3, "started_at": "2022-10-24T20:02:26.000+02:00", "completed_at": "2022-10-24T20:02:38.000+02:00"}, {"name": "Bootstrap GnuPG", "status": "completed", "conclusion": "success", "number": 4, "started_at": "2022-10-24T20:02:38.000+02:00", "completed_at": "2022-10-24T20:07:00.000+02:00"}, {"name": "Post Checkout", "status": "completed", "conclusion": "success", "number": 8, "started_at": "2022-10-24T20:07:00.000+02:00", "completed_at": "2022-10-24T20:07:01.000+02:00"}, {"name": "Complete job", "status": "completed", "conclusion": "success", "number": 9, "started_at": "2022-10-24T20:07:01.000+02:00", "completed_at": "2022-10-24T20:07:01.000+02:00"}], "check_run_url": "https://api.github.com/repos/spack/spack/check-runs/9075728083", "labels": ["macos-latest"], "runner_id": 6, "runner_name": "GitHub Actions 6", "runner_group_id": 2, "runner_group_name": "GitHub Actions"}, {"id": 9075728276, "run_id": 3314691390, "run_url": "https://api.github.com/repos/spack/spack/actions/runs/3314691390", "run_attempt": 1, "node_id": "CR_kwDOAPAIsc8AAAACHPSflA", "head_sha": "0b971a1aef2fa27574d3c7c5f1a8a2eed6c2c1ec", "url": "https://api.github.com/repos/spack/spack/actions/jobs/9075728276", "html_url": "https://github.com/spack/spack/actions/runs/3314691390/jobs/5474889391", "status": "completed", "conclusion": "success", "started_at": "2022-10-24T18:02:40Z", "completed_at": "2022-10-24T18:04:44Z", "name": "bootstrap / ubuntu-gnupg-binaries", "steps": [{"name": "Set up job", "status": "completed", "conclusion": "success", "number": 1, "started_at": "2022-10-24T20:02:39.000+02:00", "completed_at": "2022-10-24T20:02:41.000+02:00"}, {"name": "Initialize containers", "status": "completed", "conclusion": "success", "number": 2, "started_at": "2022-10-24T20:02:41.000+02:00", "completed_at": "2022-10-24T20:02:47.000+02:00"}, {"name": "Install dependencies", "status": "completed", "conclusion": "success", "number": 3, "started_at": "2022-10-24T20:02:47.000+02:00", "completed_at": "2022-10-24T20:03:17.000+02:00"}, {"name": "Checkout", "status": "completed", "conclusion": "success", "number": 4, "started_at": "2022-10-24T20:03:17.000+02:00", "completed_at": "2022-10-24T20:03:45.000+02:00"}, {"name": "Setup non-root user", "status": "completed", "conclusion": "success", "number": 5, "started_at": "2022-10-24T20:03:45.000+02:00", "completed_at": "2022-10-24T20:03:45.000+02:00"}, {"name": "Setup repo", "status": "completed", "conclusion": "success", "number": 6, "started_at": "2022-10-24T20:03:46.000+02:00", "completed_at": "2022-10-24T20:03:46.000+02:00"}, {"name": "Bootstrap GnuPG", "status": "completed", "conclusion": "success", "number": 7, "started_at": "2022-10-24T20:03:46.000+02:00", "completed_at": "2022-10-24T20:04:40.000+02:00"}, {"name": "Post Checkout", "status": "completed", "conclusion": "success", "number": 13, "started_at": "2022-10-24T20:04:40.000+02:00", "completed_at": "2022-10-24T20:04:41.000+02:00"}, {"name": "Stop containers", "status": "completed", "conclusion": "success", "number": 14, "started_at": "2022-10-24T20:04:41.000+02:00", "completed_at": "2022-10-24T20:04:42.000+02:00"}, {"name": "Complete job", "status": "completed", "conclusion": "success", "number": 15, "started_at": "2022-10-24T20:04:42.000+02:00", "completed_at": "2022-10-24T20:04:42.000+02:00"}], "check_run_url": "https://api.github.com/repos/spack/spack/check-runs/9075728276", "labels": ["ubuntu-latest"], "runner_id": 18, "runner_name": "GitHub Actions 18", "runner_group_id": 2, "runner_group_name": "GitHub Actions"}, {"id": 9075728425, "run_id": 3314691390, "run_url": "https://api.github.com/repos/spack/spack/actions/runs/3314691390", "run_attempt": 1, "node_id": "CR_kwDOAPAIsc8AAAACHPSgKQ", "head_sha": "0b971a1aef2fa27574d3c7c5f1a8a2eed6c2c1ec", "url": "https://api.github.com/repos/spack/spack/actions/jobs/9075728425", "html_url": "https://github.com/spack/spack/actions/runs/3314691390/jobs/5474889519", "status": "completed", "conclusion": "success", "started_at": "2022-10-24T18:03:58Z", "completed_at": "2022-10-24T18:05:24Z", "name": "bootstrap / ubuntu-gnupg-sources", "steps": [{"name": "Set up job", "status": "completed", "conclusion": "success", "number": 1, "started_at": "2022-10-24T20:03:57.000+02:00", "completed_at": "2022-10-24T20:03:58.000+02:00"}, {"name": "Initialize containers", "status": "completed", "conclusion": "success", "number": 2, "started_at": "2022-10-24T20:03:58.000+02:00", "completed_at": "2022-10-24T20:04:02.000+02:00"}, {"name": "Install dependencies", "status": "completed", "conclusion": "success", "number": 3, "started_at": "2022-10-24T20:04:02.000+02:00", "completed_at": "2022-10-24T20:04:18.000+02:00"}, {"name": "Checkout", "status": "completed", "conclusion": "success", "number": 4, "started_at": "2022-10-24T20:04:19.000+02:00", "completed_at": "2022-10-24T20:04:40.000+02:00"}, {"name": "Setup non-root user", "status": "completed", "conclusion": "success", "number": 5, "started_at": "2022-10-24T20:04:41.000+02:00", "completed_at": "2022-10-24T20:04:41.000+02:00"}, {"name": "Setup repo", "status": "completed", "conclusion": "success", "number": 6, "started_at": "2022-10-24T20:04:41.000+02:00", "completed_at": "2022-10-24T20:04:41.000+02:00"}, {"name": "Bootstrap GnuPG", "status": "completed", "conclusion": "success", "number": 7, "started_at": "2022-10-24T20:04:41.000+02:00", "completed_at": "2022-10-24T20:05:22.000+02:00"}, {"name": "Post Checkout", "status": "completed", "conclusion": "success", "number": 13, "started_at": "2022-10-24T20:05:22.000+02:00", "completed_at": "2022-10-24T20:05:22.000+02:00"}, {"name": "Stop containers", "status": "completed", "conclusion": "success", "number": 14, "started_at": "2022-10-24T20:05:23.000+02:00", "completed_at": "2022-10-24T20:05:23.000+02:00"}, {"name": "Complete job", "status": "completed", "conclusion": "success", "number": 15, "started_at": "2022-10-24T20:05:23.000+02:00", "completed_at": "2022-10-24T20:05:23.000+02:00"}], "check_run_url": "https://api.github.com/repos/spack/spack/check-runs/9075728425", "labels": ["ubuntu-latest"], "runner_id": 1, "runner_name": "Hosted Agent", "runner_group_id": 2, "runner_group_name": "GitHub Actions"}, {"id": 9075728602, "run_id": 3314691390, "run_url": "https://api.github.com/repos/spack/spack/actions/runs/3314691390", "run_attempt": 1, "node_id": "CR_kwDOAPAIsc8AAAACHPSg2g", "head_sha": "0b971a1aef2fa27574d3c7c5f1a8a2eed6c2c1ec", "url": "https://api.github.com/repos/spack/spack/actions/jobs/9075728602", "html_url": "https://github.com/spack/spack/actions/runs/3314691390/jobs/5474889628", "status": "completed", "conclusion": "success", "started_at": "2022-10-24T18:04:41Z", "completed_at": "2022-10-24T18:06:35Z", "name": "bootstrap / macos-gnupg-sources", "steps": [{"name": "Set up job", "status": "completed", "conclusion": "success", "number": 1, "started_at": "2022-10-24T20:04:40.000+02:00", "completed_at": "2022-10-24T20:04:42.000+02:00"}, {"name": "Install dependencies", "status": "completed", "conclusion": "success", "number": 2, "started_at": "2022-10-24T20:04:43.000+02:00", "completed_at": "2022-10-24T20:04:59.000+02:00"}, {"name": "Checkout", "status": "completed", "conclusion": "success", "number": 3, "started_at": "2022-10-24T20:05:00.000+02:00", "completed_at": "2022-10-24T20:05:13.000+02:00"}, {"name": "Bootstrap GnuPG", "status": "completed", "conclusion": "success", "number": 4, "started_at": "2022-10-24T20:05:14.000+02:00", "completed_at": "2022-10-24T20:06:31.000+02:00"}, {"name": "Post Checkout", "status": "completed", "conclusion": "success", "number": 8, "started_at": "2022-10-24T20:06:32.000+02:00", "completed_at": "2022-10-24T20:06:32.000+02:00"}, {"name": "Complete job", "status": "completed", "conclusion": "success", "number": 9, "started_at": "2022-10-24T20:06:32.000+02:00", "completed_at": "2022-10-24T20:06:32.000+02:00"}], "check_run_url": "https://api.github.com/repos/spack/spack/check-runs/9075728602", "labels": ["macos-latest"], "runner_id": 4, "runner_name": "GitHub Actions 4", "runner_group_id": 2, "runner_group_name": "GitHub Actions"}]}