{"total_count": 9, "jobs": [{"id": 9722656585, "run_id": 3554903828, "run_url": "https://api.github.com/repos/spack/spack/actions/runs/3554903828", "run_attempt": 1, "node_id": "CR_kwDOAPAIsc8AAAACQ4P3SQ", "head_sha": "fbf2b2a2d9850114be86bb7494378d5b4b57ae3d", "url": "https://api.github.com/repos/spack/spack/actions/jobs/9722656585", "html_url": "https://github.com/spack/spack/actions/runs/3554903828/jobs/5971282017", "status": "completed", "conclusion": "success", "started_at": "2022-11-26T18:32:56Z", "completed_at": "2022-11-26T18:32:58Z", "name": "changes", "steps": [{"name": "Set up job", "status": "completed", "conclusion": "success", "number": 1, "started_at": "2022-11-26T19:32:56.000+01:00", "completed_at": "2022-11-26T19:32:57.000+01:00"}, {"name": "Run actions/checkout@93ea575cb5d8a053eaa0ac8fa3b40d7e05a33cc8", "status": "completed", "conclusion": "skipped", "number": 2, "started_at": "2022-11-26T19:32:57.000+01:00", "completed_at": "2022-11-26T19:32:57.000+01:00"}, {"name": "Run dorny/paths-filter@4512585405083f25c027a35db413c2b3b9006d50", "status": "completed", "conclusion": "success", "number": 3, "started_at": "2022-11-26T19:32:57.000+01:00", "completed_at": "2022-11-26T19:32:57.000+01:00"}, {"name": "Complete job", "status": "completed", "conclusion": "success", "number": 4, "started_at": "2022-11-26T19:32:57.000+01:00", "completed_at": "2022-11-26T19:32:57.000+01:00"}], "check_run_url": "https://api.github.com/repos/spack/spack/check-runs/9722656585", "labels": ["ubuntu-latest"], "runner_id": 2, "runner_name": "GitHub Actions 2", "runner_group_id": 2, "runner_group_name": "GitHub Actions"}, {"id": 9722657433, "run_id": 3554903828, "run_url": "https://api.github.com/repos/spack/spack/actions/runs/3554903828", "run_attempt": 1, "node_id": "CR_kwDOAPAIsc8AAAACQ4P6mQ", "head_sha": "fbf2b2a2d9850114be86bb7494378d5b4b57ae3d", "url": "https://api.github.com/repos/spack/spack/actions/jobs/9722657433", "html_url": "https://github.com/spack/spack/actions/runs/3554903828/jobs/5971282796", "status": "completed", "conclusion": "success", "started_at": "2022-11-26T18:33:07Z", "completed_at": "2022-11-26T18:33:49Z", "name": "prechecks / validate", "steps": [{"name": "Set up job", "status": "completed", "conclusion": "success", "number": 1, "started_at": "2022-11-26T19:33:06.000+01:00", "completed_at": "2022-11-26T19:33:08.000+01:00"}, {"name": "Run actions/checkout@93ea575cb5d8a053eaa0ac8fa3b40d7e05a33cc8", "status": "completed", "conclusion": "success", "number": 2, "started_at": "2022-11-26T19:33:08.000+01:00", "completed_at": "2022-11-26T19:33:12.000+01:00"}, {"name": "Run actions/setup-python@13ae5bb136fac2878aff31522b9efb785519f984", "status": "completed", "conclusion": "success", "number": 3, "started_at": "2022-11-26T19:33:13.000+01:00", "completed_at": "2022-11-26T19:33:16.000+01:00"}, {"name": "Install Python Packages", "status": "completed", "conclusion": "success", "number": 4, "started_at": "2022-11-26T19:33:17.000+01:00", "completed_at": "2022-11-26T19:33:19.000+01:00"}, {"name": "vermin (Spack's Core)", "status": "completed", "conclusion": "success", "number": 5, "started_at": "2022-11-26T19:33:19.000+01:00", "completed_at": "2022-11-26T19:33:26.000+01:00"}, {"name": "vermin (Repositories)", "status": "completed", "conclusion": "success", "number": 6, "started_at": "2022-11-26T19:33:26.000+01:00", "completed_at": "2022-11-26T19:33:46.000+01:00"}, {"name": "Post Run actions/setup-python@13ae5bb136fac2878aff31522b9efb785519f984", "status": "completed", "conclusion": "success", "number": 11, "started_at": "2022-11-26T19:33:47.000+01:00", "completed_at": "2022-11-26T19:33:47.000+01:00"}, {"name": "Post Run actions/checkout@93ea575cb5d8a053eaa0ac8fa3b40d7e05a33cc8", "status": "completed", "conclusion": "success", "number": 12, "started_at": "2022-11-26T19:33:47.000+01:00", "completed_at": "2022-11-26T19:33:47.000+01:00"}, {"name": "Complete job", "status": "completed", "conclusion": "success", "number": 13, "started_at": "2022-11-26T19:33:47.000+01:00", "completed_at": "2022-11-26T19:33:47.000+01:00"}], "check_run_url": "https://api.github.com/repos/spack/spack/check-runs/9722657433", "labels": ["ubuntu-latest"], "runner_id": 3, "runner_name": "GitHub Actions 3", "runner_group_id": 2, "runner_group_name": "GitHub Actions"}, {"id": 9722657481, "run_id": 3554903828, "run_url": "https://api.github.com/repos/spack/spack/actions/runs/3554903828", "run_attempt": 1, "node_id": "CR_kwDOAPAIsc8AAAACQ4P6yQ", "head_sha": "fbf2b2a2d9850114be86bb7494378d5b4b57ae3d", "url": "https://api.github.com/repos/spack/spack/actions/jobs/9722657481", "html_url": "https://github.com/spack/spack/actions/runs/3554903828/jobs/5971282841", "status": "completed", "conclusion": "failure", "started_at": "2022-11-26T18:33:05Z", "completed_at": "2022-11-26T18:34:09Z", "name": "prechecks / style", "steps": [{"name": "Set up job", "status": "completed", "conclusion": "success", "number": 1, "started_at": "2022-11-26T19:33:05.000+01:00", "completed_at": "2022-11-26T19:33:06.000+01:00"}, {"name": "Run actions/checkout@93ea575cb5d8a053eaa0ac8fa3b40d7e05a33cc8", "status": "completed", "conclusion": "success", "number": 2, "started_at": "2022-11-26T19:33:06.000+01:00", "completed_at": "2022-11-26T19:33:29.000+01:00"}, {"name": "Run actions/setup-python@13ae5bb136fac2878aff31522b9efb785519f984", "status": "completed", "conclusion": "success", "number": 3, "started_at": "2022-11-26T19:33:30.000+01:00", "completed_at": "2022-11-26T19:33:35.000+01:00"}, {"name": "Install Python packages", "status": "completed", "conclusion": "success", "number": 4, "started_at": "2022-11-26T19:33:35.000+01:00", "completed_at": "2022-11-26T19:33:42.000+01:00"}, {"name": "Setup git configuration", "status": "completed", "conclusion": "success", "number": 5, "started_at": "2022-11-26T19:33:42.000+01:00", "completed_at": "2022-11-26T19:33:42.000+01:00"}, {"name": "Run style tests", "status": "completed", "conclusion": "failure", "number": 6, "started_at": "2022-11-26T19:33:42.000+01:00", "completed_at": "2022-11-26T19:34:08.000+01:00"}, {"name": "Post Run actions/setup-python@13ae5bb136fac2878aff31522b9efb785519f984", "status": "completed", "conclusion": "skipped", "number": 11, "started_at": "2022-11-26T19:34:09.000+01:00", "completed_at": "2022-11-26T19:34:09.000+01:00"}, {"name": "Post Run actions/checkout@93ea575cb5d8a053eaa0ac8fa3b40d7e05a33cc8", "status": "completed", "conclusion": "success", "number": 12, "started_at": "2022-11-26T19:34:09.000+01:00", "completed_at": "2022-11-26T19:34:09.000+01:00"}, {"name": "Complete job", "status": "completed", "conclusion": "success", "number": 13, "started_at": "2022-11-26T19:34:09.000+01:00", "completed_at": "2022-11-26T19:34:09.000+01:00"}], "check_run_url": "https://api.github.com/repos/spack/spack/check-runs/9722657481", "labels": ["ubuntu-latest"], "runner_id": 2, "runner_name": "GitHub Actions 2", "runner_group_id": 2, "runner_group_name": "GitHub Actions"}, {"id": 9722657525, "run_id": 3554903828, "run_url": "https://api.github.com/repos/spack/spack/actions/runs/3554903828", "run_attempt": 1, "node_id": "CR_kwDOAPAIsc8AAAACQ4P69Q", "head_sha": "fbf2b2a2d9850114be86bb7494378d5b4b57ae3d", "url": "https://api.github.com/repos/spack/spack/actions/jobs/9722657525", "html_url": "https://github.com/spack/spack/actions/runs/3554903828/jobs/5971282882", "status": "completed", "conclusion": "success", "started_at": "2022-11-26T18:33:06Z", "completed_at": "2022-11-26T18:34:55Z", "name": "prechecks / audit / package-audits", "steps": [{"name": "Set up job", "status": "completed", "conclusion": "success", "number": 1, "started_at": "2022-11-26T19:33:06.000+01:00", "completed_at": "2022-11-26T19:33:08.000+01:00"}, {"name": "Run actions/checkout@93ea575cb5d8a053eaa0ac8fa3b40d7e05a33cc8", "status": "completed", "conclusion": "success", "number": 2, "started_at": "2022-11-26T19:33:08.000+01:00", "completed_at": "2022-11-26T19:33:12.000+01:00"}, {"name": "Run actions/setup-python@13ae5bb136fac2878aff31522b9efb785519f984", "status": "completed", "conclusion": "success", "number": 3, "started_at": "2022-11-26T19:33:13.000+01:00", "completed_at": "2022-11-26T19:33:13.000+01:00"}, {"name": "Install Python packages", "status": "completed", "conclusion": "success", "number": 4, "started_at": "2022-11-26T19:33:13.000+01:00", "completed_at": "2022-11-26T19:33:23.000+01:00"}, {"name": "Package audits (with coverage)", "status": "completed", "conclusion": "skipped", "number": 5, "started_at": "2022-11-26T19:33:23.000+01:00", "completed_at": "2022-11-26T19:33:23.000+01:00"}, {"name": "Package audits (without coverage)", "status": "completed", "conclusion": "success", "number": 6, "started_at": "2022-11-26T19:33:23.000+01:00", "completed_at": "2022-11-26T19:34:52.000+01:00"}, {"name": "Run codecov/codecov-action@d9f34f8cd5cb3b3eb79b3e4b5dae3a16df499a70", "status": "completed", "conclusion": "skipped", "number": 7, "started_at": "2022-11-26T19:34:53.000+01:00", "completed_at": "2022-11-26T19:34:53.000+01:00"}, {"name": "Post Run actions/setup-python@13ae5bb136fac2878aff31522b9efb785519f984", "status": "completed", "conclusion": "success", "number": 13, "started_at": "2022-11-26T19:34:53.000+01:00", "completed_at": "2022-11-26T19:34:53.000+01:00"}, {"name": "Post Run actions/checkout@93ea575cb5d8a053eaa0ac8fa3b40d7e05a33cc8", "status": "completed", "conclusion": "success", "number": 14, "started_at": "2022-11-26T19:34:53.000+01:00", "completed_at": "2022-11-26T19:34:53.000+01:00"}, {"name": "Complete job", "status": "completed", "conclusion": "success", "number": 15, "started_at": "2022-11-26T19:34:53.000+01:00", "completed_at": "2022-11-26T19:34:53.000+01:00"}], "check_run_url": "https://api.github.com/repos/spack/spack/check-runs/9722657525", "labels": ["ubuntu-latest"], "runner_id": 4, "runner_name": "GitHub Actions 4", "runner_group_id": 2, "runner_group_name": "GitHub Actions"}, {"id": 9722669358, "run_id": 3554903828, "run_url": "https://api.github.com/repos/spack/spack/actions/runs/3554903828", "run_attempt": 1, "node_id": "CR_kwDOAPAIsc8AAAACQ4QpLg", "head_sha": "fbf2b2a2d9850114be86bb7494378d5b4b57ae3d", "url": "https://api.github.com/repos/spack/spack/actions/jobs/9722669358", "html_url": "https://github.com/spack/spack/actions/runs/3554903828/jobs/5971293456", "status": "completed", "conclusion": "skipped", "started_at": "2022-11-26T18:34:56Z", "completed_at": "2022-11-26T18:34:56Z", "name": "all-prechecks", "steps": [], "check_run_url": "https://api.github.com/repos/spack/spack/check-runs/9722669358", "labels": [], "runner_id": null, "runner_name": null, "runner_group_id": null, "runner_group_name": null}, {"id": 9722669410, "run_id": 3554903828, "run_url": "https://api.github.com/repos/spack/spack/actions/runs/3554903828", "run_attempt": 1, "node_id": "CR_kwDOAPAIsc8AAAACQ4QpYg", "head_sha": "fbf2b2a2d9850114be86bb7494378d5b4b57ae3d", "url": "https://api.github.com/repos/spack/spack/actions/jobs/9722669410", "html_url": "https://github.com/spack/spack/actions/runs/3554903828/jobs/5971293502", "status": "completed", "conclusion": "skipped", "started_at": "2022-11-26T18:34:56Z", "completed_at": "2022-11-26T18:34:56Z", "name": "unit-tests", "steps": [], "check_run_url": "https://api.github.com/repos/spack/spack/check-runs/9722669410", "labels": [], "runner_id": null, "runner_name": null, "runner_group_id": null, "runner_group_name": null}, {"id": 9722669462, "run_id": 3554903828, "run_url": "https://api.github.com/repos/spack/spack/actions/runs/3554903828", "run_attempt": 1, "node_id": "CR_kwDOAPAIsc8AAAACQ4Qplg", "head_sha": "fbf2b2a2d9850114be86bb7494378d5b4b57ae3d", "url": "https://api.github.com/repos/spack/spack/actions/jobs/9722669462", "html_url": "https://github.com/spack/spack/actions/runs/3554903828/jobs/5971293549", "status": "completed", "conclusion": "skipped", "started_at": "2022-11-26T18:34:57Z", "completed_at": "2022-11-26T18:34:57Z", "name": "windows", "steps": [], "check_run_url": "https://api.github.com/repos/spack/spack/check-runs/9722669462", "labels": [], "runner_id": null, "runner_name": null, "runner_group_id": null, "runner_group_name": null}, {"id": 9722669508, "run_id": 3554903828, "run_url": "https://api.github.com/repos/spack/spack/actions/runs/3554903828", "run_attempt": 1, "node_id": "CR_kwDOAPAIsc8AAAACQ4QpxA", "head_sha": "fbf2b2a2d9850114be86bb7494378d5b4b57ae3d", "url": "https://api.github.com/repos/spack/spack/actions/jobs/9722669508", "html_url": "https://github.com/spack/spack/actions/runs/3554903828/jobs/5971293589", "status": "completed", "conclusion": "skipped", "started_at": "2022-11-26T18:34:57Z", "completed_at": "2022-11-26T18:34:57Z", "name": "bootstrap", "steps": [], "check_run_url": "https://api.github.com/repos/spack/spack/check-runs/9722669508", "labels": [], "runner_id": null, "runner_name": null, "runner_group_id": null, "runner_group_name": null}, {"id": 9722669566, "run_id": 3554903828, "run_url": "https://api.github.com/repos/spack/spack/actions/runs/3554903828", "run_attempt": 1, "node_id": "CR_kwDOAPAIsc8AAAACQ4Qp_g", "head_sha": "fbf2b2a2d9850114be86bb7494378d5b4b57ae3d", "url": "https://api.github.com/repos/spack/spack/actions/jobs/9722669566", "html_url": "https://github.com/spack/spack/actions/runs/3554903828/jobs/5971293641", "status": "completed", "conclusion": "skipped", "started_at": "2022-11-26T18:34:58Z", "completed_at": "2022-11-26T18:34:58Z", "name": "all", "steps": [], "check_run_url": "https://api.github.com/repos/spack/spack/check-runs/9722669566", "labels": [], "runner_id": null, "runner_name": null, "runner_group_id": null, "runner_group_name": null}]}